Workbook

Sheet Theme Summary
A1: Conversation View feedback - theme summary
A2: Counts are unique feedback records confidently classified into each sub-theme. 'Number of Comments' is a live COUNT over the matching sub-theme sheet, so the summary always reconciles with the detail.
A4: Scope of analysis
A5: Total feedback records reviewed | B5: 757
A6: Feedback date range | B6: 14 Oct 2020 to 18 Aug 2026
A7: Quarters covered | B7: 24 (Q4 2020 to Q3 2026)
A8: Unique accounts | B8: 654
A9: Records classified into at least one sub-theme | B9: 460 | C9: =B9/B5 -> 0.60766182 | D9: of all records reviewed
A10: Records not classified | B10: =COUNT('Unclassified Feedback'!$A$2:$A$2000) -> 297 | C10: =B10/B5 -> 0.39233818 | D10: specific problem not identifiable from the text - see Unclassified Feedback sheet
A11: Total sub-theme assignments (a record may span several) | B11: =F29 -> 545
A12: Records mapped to more than one sub-theme | B12: 80 | C12: =B12/B9 -> 0.17391304 | D12: drives the gap between records classified and total assignments
A13: Sub-themes with at least one classified comment | B13: =COUNTIF($F$16:$F$28,">0")&" of "&COUNTA($B$16:$B$28) -> 12 of 13
A15: Theme | B15: Sub-theme | C15: Problem / Story | D15: Top comment highlights and account | E15: Comment | F15: Number of Comments
A16: Thread navigation & message discovery | B16: Message ordering | C16: I can't view the conversation in the chronological order that feels natural to me. | D16: "there is no flow in the message. top to bottom. new message comes in the middle instead" - Account 5197887, 2026-08-11 "the latest response pops up in the middle" - Account 9166325, 2026-05-04 "The email threads arent in chronological order" - Account 162102, 2025-08-03 | F16: =COUNT('Message Ordering'!$B$2:$B$2000) -> 94
A17: Thread navigation & message discovery | B17: Jump to latest message | C17: I have to manually scroll through long threads to find the newest message, and currently I am landed on the last unread message. | D17: "I have to scroll through all the past emails to find the latest one" - Account 7980726, 2026-03-19 "in a trailed email, it is very hard to find the last one that came in" - Account 4866745, 2026-05-08 "very hard to se the most recent message" - Account 10662219, 2026-06-30 | F17: =COUNT('Jump to Latest'!$B$2:$B$2000) -> 69
A18: Thread navigation & message discovery | B18: Finding a specific message | C18: I have to search through or expand a long thread to find a specific earlier message or piece of information. | D18: "it is more of a struggle to find a specific one by the date it was sent" - Account 10767743, 2026-07-20 "It takes an age to find a particular email" - Account 3836964, 2025-08-15 "they pile up and it is hard to find an email within the thread" - Account 3374249, 2026-02-19 | F18: =COUNT('Find Specific Message'!$B$2:$B$2000) -> 80
A19: Thread navigation & message discovery | B19: Read/unread visibility | C19: I can't easily tell which messages inside a thread I have already read. | D19: No comments confidently classified into this sub-theme. | F19: =COUNT('Read-Unread Visibility'!$B$2:$B$2000) -> 0
A20: Message actions | B20: Mark individual message unread | C20: I can't manage the read state of a specific email independently from the rest of the thread. | D20: "Mark individual emails unread rather than full threads" - Account 1348064, 2022-07-21 "you can mark just one email as unread from a thread" - Account 6764889, 2026-02-09 "I would like to be able to mark a read email as new" - Account 6712333, 2025-11-25 | F20: =COUNT('Mark Message Unread'!$B$2:$B$2000) -> 3
A21: Conversation grouping & boundaries | B21: Disable Conversation View | C21: I'm forced to consume emails as grouped conversations even when I prefer individual messages. | D21: "You cannot change email from conversation view to single email view" - Account 9235848, 2026-05-06 "Provide an options where emails do not need to be grouped by thread, but can be separated into their own email" - Account 216696, 2026-04-20 "I cant change from conversation mode to single email" - Account 7956637, 2026-03-23 | E21: Fixed | F21: =COUNT('Disable Conversation'!$B$2:$B$2000) -> 197
A22: Conversation grouping & boundaries | B22: Separate conversation branches | C22: Replies and forwards meant for different audiences or contexts get appended to the same conversation, making it difficult to distinguish separate discussion branches and understand who saw what. | D22: "If one forwards an email to someone else, it should not then be part of the old email chain" - Account 6712333, 2025-11-25 "It groups emails and histories under the same subject; the recipients are sometimes different" - Account 6755629, 2026-02-07 "they are grouped under one even I change recipients in responding emails" - Account 3726421, 2025-03-08 | F22: =COUNT('Separate Branches'!$B$2:$B$2000) -> 23
A23: Thread readability & structure | B23: Nested / quoted content readability | C23: When an email has been replied to or forwarded repeatedly, the quoted history keeps getting narrower or hidden until older content becomes extremely difficult or impossible to read. | D23: "the email history makes it harder to check the messages because they keep "shrinking" towards the right-hand side" - Account 7914516, 2026-05-11 "Reading through a quoted email thread that you weren't part of is practically impossible" - Account 648473, 2026-06-16 "The message block becomes thinner and thinner, until each word in the email becomes a new line" - Account 1193270, 2022-06-21 | F23: =COUNT('Quoted Readability'!$B$2:$B$2000) -> 9
A24: Attachments in threads | B24: Attachment discovery & access | C24: I have to search through individual messages to find attachments in a long conversation. | D24: "THE ATTACHMENTS FROM OTJHER EMAILS ARE IMPOSSIBLE TO FIND" - Account 7436174, 2025-10-24 "you have to scroll to the bottom of the entire thread in order to see the attachments for a recent response" - Account 8023722, 2026-04-03 "struggling to find a file attached to an email in the thread" - Account 7245148, 2026-05-06 | F24: =COUNT('Attachment Discovery'!$B$2:$B$2000) -> 29
A25: Attachments in threads | B25: Attachment carry-over | C25: When I reply or forward within a thread, I can't easily control whether attachments from earlier messages should be included or excluded. | D25: "attached files do not come through in the email when they are replied to" - Account 6276279, 2025-01-06 | F25: =COUNT('Attachment Carry-over'!$B$2:$B$2000) -> 1
A26: Thread reliability | B26: Message rendering | C26: When I open older messages in a thread, content can appear duplicated, hidden behind ellipses, badly formatted, or with images missing, so I can't trust that I'm seeing the complete original email. | D26: "the newest email in a thread does not load and i cant see it until i press the reply button" - Account 3305982, 2026-05-04 "The root email is repeated in the chain over and over again" - Account 7578799, 2026-04-16 "Sometimes the text of email threads vanish under ... ellipses" - Account 3104383, 2026-05-16 | F26: =COUNT('Message Rendering'!$B$2:$B$2000) -> 29
A27: Thread sharing | B27: Attach conversation to a new email | C27: When I want to share an existing email conversation with someone new, I can't attach the full thread to a new email as one object. | D27: "It is not possible to attach email threads to new emails" - Account 8525088, 2026-06-12 "Give an option to forward email threads as an attachment" - Account 9494030, 2026-08-18 | F27: =COUNT('Attach Conversation'!$B$2:$B$2000) -> 2
A28: Thread sharing | B28: Print full conversation | C28: When I print an email conversation, I can't reliably get one clean copy of the complete thread without messages being missed or duplicated. | D28: "In single message print .... it should print whole thread. In general print email ... it should avoid duplication print of same message" - Account 6178215, 2025-11-24 "it prints the whole string, repeating some messages multiple times" - Account 167088, 2021-04-04 "Most email threads can't be printed--it's a blank screen when I choose "print conversation."" - Account 917360, 2022-05-11 | F28: =COUNT('Print Conversation'!$B$2:$B$2000) -> 9
D29: Total classified records (a record may appear under more than one sub-theme) | F29: =SUM(F16:F28) -> 545

Sheet Quarterly Trend
A1: Classified comments per sub-theme, by quarter (newest to oldest)
A2: Quarter derived from Feedback Date. Cells are COUNTIFS over the sub-theme sheets, so they reconcile with the detail sheets.
A4: Theme | B4: Sub-theme | C4: Q3 2026 | D4: Q2 2026 | E4: Q1 2026 | F4: Q4 2025 | G4: Q3 2025 | H4: Q2 2025 | I4: Q1 2025 | J4: Q4 2024 | K4: Q3 2024 | L4: Q2 2024 | M4: Q1 2024 | N4: Q4 2023 | O4: Q3 2023 | P4: Q2 2023 | Q4: Q1 2023 | R4: Q4 2022 | S4: Q3 2022 | T4: Q2 2022 | U4: Q1 2022 | V4: Q4 2021 | W4: Q3 2021 | X4: Q2 2021 | Y4: Q1 2021 | Z4: Q4 2020
A5: Thread navigation & message discovery | B5: Message ordering | C5: =COUNTIFS('Message Ordering'!$C$2:$C$2000,">="&DATE(2026,7,1),'Message Ordering'!$C$2:$C$2000,"<="&DATE(2026,9,30)) -> 4 | D5: =COUNTIFS('Message Ordering'!$C$2:$C$2000,">="&DATE(2026,4,1),'Message Ordering'!$C$2:$C$2000,"<="&DATE(2026,6,30)) -> 6 | E5: =COUNTIFS('Message Ordering'!$C$2:$C$2000,">="&DATE(2026,1,1),'Message Ordering'!$C$2:$C$2000,"<="&DATE(2026,3,31)) -> 3 | F5: =COUNTIFS('Message Ordering'!$C$2:$C$2000,">="&DATE(2025,10,1),'Message Ordering'!$C$2:$C$2000,"<="&DATE(2025,12,31)) -> 7 | G5: =COUNTIFS('Message Ordering'!$C$2:$C$2000,">="&DATE(2025,7,1),'Message Ordering'!$C$2:$C$2000,"<="&DATE(2025,9,30)) -> 5 | H5: =COUNTIFS('Message Ordering'!$C$2:$C$2000,">="&DATE(2025,4,1),'Message Ordering'!$C$2:$C$2000,"<="&DATE(2025,6,30)) -> 5 | I5: =COUNTIFS('Message Ordering'!$C$2:$C$2000,">="&DATE(2025,1,1),'Message Ordering'!$C$2:$C$2000,"<="&DATE(2025,3,31)) -> 5 | J5: =COUNTIFS('Message Ordering'!$C$2:$C$2000,">="&DATE(2024,10,1),'Message Ordering'!$C$2:$C$2000,"<="&DATE(2024,12,31)) -> 3 | K5: =COUNTIFS('Message Ordering'!$C$2:$C$2000,">="&DATE(2024,7,1),'Message Ordering'!$C$2:$C$2000,"<="&DATE(2024,9,30)) -> 6 | L5: =COUNTIFS('Message Ordering'!$C$2:$C$2000,">="&DATE(2024,4,1),'Message Ordering'!$C$2:$C$2000,"<="&DATE(2024,6,30)) -> 5 | M5: =COUNTIFS('Message Ordering'!$C$2:$C$2000,">="&DATE(2024,1,1),'Message Ordering'!$C$2:$C$2000,"<="&DATE(2024,3,31)) -> 5 | N5: =COUNTIFS('Message Ordering'!$C$2:$C$2000,">="&DATE(2023,10,1),'Message Ordering'!$C$2:$C$2000,"<="&DATE(2023,12,31)) -> 3 | O5: =COUNTIFS('Message Ordering'!$C$2:$C$2000,">="&DATE(2023,7,1),'Message Ordering'!$C$2:$C$2000,"<="&DATE(2023,9,30)) -> 7 | P5: =COUNTIFS('Message Ordering'!$C$2:$C$2000,">="&DATE(2023,4,1),'Message Ordering'!$C$2:$C$2000,"<="&DATE(2023,6,30)) -> 5 | Q5: =COUNTIFS('Message Ordering'!$C$2:$C$2000,">="&DATE(2023,1,1),'Message Ordering'!$C$2:$C$2000,"<="&DATE(2023,3,31)) -> 1 | R5: =COUNTIFS('Message Ordering'!$C$2:$C$2000,">="&DATE(2022,10,1),'Message Ordering'!$C$2:$C$2000,"<="&DATE(2022,12,31)) -> 3 | S5: =COUNTIFS('Message Ordering'!$C$2:$C$2000,">="&DATE(2022,7,1),'Message Ordering'!$C$2:$C$2000,"<="&DATE(2022,9,30)) -> 1 | T5: =COUNTIFS('Message Ordering'!$C$2:$C$2000,">="&DATE(2022,4,1),'Message Ordering'!$C$2:$C$2000,"<="&DATE(2022,6,30)) -> 3 | U5: =COUNTIFS('Message Ordering'!$C$2:$C$2000,">="&DATE(2022,1,1),'Message Ordering'!$C$2:$C$2000,"<="&DATE(2022,3,31)) -> 8 | V5: =COUNTIFS('Message Ordering'!$C$2:$C$2000,">="&DATE(2021,10,1),'Message Ordering'!$C$2:$C$2000,"<="&DATE(2021,12,31)) -> 3 | W5: =COUNTIFS('Message Ordering'!$C$2:$C$2000,">="&DATE(2021,7,1),'Message Ordering'!$C$2:$C$2000,"<="&DATE(2021,9,30)) -> 0 | X5: =COUNTIFS('Message Ordering'!$C$2:$C$2000,">="&DATE(2021,4,1),'Message Ordering'!$C$2:$C$2000,"<="&DATE(2021,6,30)) -> 5 | Y5: =COUNTIFS('Message Ordering'!$C$2:$C$2000,">="&DATE(2021,1,1),'Message Ordering'!$C$2:$C$2000,"<="&DATE(2021,3,31)) -> 1 | Z5: =COUNTIFS('Message Ordering'!$C$2:$C$2000,">="&DATE(2020,10,1),'Message Ordering'!$C$2:$C$2000,"<="&DATE(2020,12,31)) -> 0
A6: Thread navigation & message discovery | B6: Jump to latest message | C6: =COUNTIFS('Jump to Latest'!$C$2:$C$2000,">="&DATE(2026,7,1),'Jump to Latest'!$C$2:$C$2000,"<="&DATE(2026,9,30)) -> 2 | D6: =COUNTIFS('Jump to Latest'!$C$2:$C$2000,">="&DATE(2026,4,1),'Jump to Latest'!$C$2:$C$2000,"<="&DATE(2026,6,30)) -> 6 | E6: =COUNTIFS('Jump to Latest'!$C$2:$C$2000,">="&DATE(2026,1,1),'Jump to Latest'!$C$2:$C$2000,"<="&DATE(2026,3,31)) -> 4 | F6: =COUNTIFS('Jump to Latest'!$C$2:$C$2000,">="&DATE(2025,10,1),'Jump to Latest'!$C$2:$C$2000,"<="&DATE(2025,12,31)) -> 1 | G6: =COUNTIFS('Jump to Latest'!$C$2:$C$2000,">="&DATE(2025,7,1),'Jump to Latest'!$C$2:$C$2000,"<="&DATE(2025,9,30)) -> 2 | H6: =COUNTIFS('Jump to Latest'!$C$2:$C$2000,">="&DATE(2025,4,1),'Jump to Latest'!$C$2:$C$2000,"<="&DATE(2025,6,30)) -> 2 | I6: =COUNTIFS('Jump to Latest'!$C$2:$C$2000,">="&DATE(2025,1,1),'Jump to Latest'!$C$2:$C$2000,"<="&DATE(2025,3,31)) -> 1 | J6: =COUNTIFS('Jump to Latest'!$C$2:$C$2000,">="&DATE(2024,10,1),'Jump to Latest'!$C$2:$C$2000,"<="&DATE(2024,12,31)) -> 2 | K6: =COUNTIFS('Jump to Latest'!$C$2:$C$2000,">="&DATE(2024,7,1),'Jump to Latest'!$C$2:$C$2000,"<="&DATE(2024,9,30)) -> 2 | L6: =COUNTIFS('Jump to Latest'!$C$2:$C$2000,">="&DATE(2024,4,1),'Jump to Latest'!$C$2:$C$2000,"<="&DATE(2024,6,30)) -> 0 | M6: =COUNTIFS('Jump to Latest'!$C$2:$C$2000,">="&DATE(2024,1,1),'Jump to Latest'!$C$2:$C$2000,"<="&DATE(2024,3,31)) -> 1 | N6: =COUNTIFS('Jump to Latest'!$C$2:$C$2000,">="&DATE(2023,10,1),'Jump to Latest'!$C$2:$C$2000,"<="&DATE(2023,12,31)) -> 1 | O6: =COUNTIFS('Jump to Latest'!$C$2:$C$2000,">="&DATE(2023,7,1),'Jump to Latest'!$C$2:$C$2000,"<="&DATE(2023,9,30)) -> 3 | P6: =COUNTIFS('Jump to Latest'!$C$2:$C$2000,">="&DATE(2023,4,1),'Jump to Latest'!$C$2:$C$2000,"<="&DATE(2023,6,30)) -> 9 | Q6: =COUNTIFS('Jump to Latest'!$C$2:$C$2000,">="&DATE(2023,1,1),'Jump to Latest'!$C$2:$C$2000,"<="&DATE(2023,3,31)) -> 6 | R6: =COUNTIFS('Jump to Latest'!$C$2:$C$2000,">="&DATE(2022,10,1),'Jump to Latest'!$C$2:$C$2000,"<="&DATE(2022,12,31)) -> 3 | S6: =COUNTIFS('Jump to Latest'!$C$2:$C$2000,">="&DATE(2022,7,1),'Jump to Latest'!$C$2:$C$2000,"<="&DATE(2022,9,30)) -> 2 | T6: =COUNTIFS('Jump to Latest'!$C$2:$C$2000,">="&DATE(2022,4,1),'Jump to Latest'!$C$2:$C$2000,"<="&DATE(2022,6,30)) -> 8 | U6: =COUNTIFS('Jump to Latest'!$C$2:$C$2000,">="&DATE(2022,1,1),'Jump to Latest'!$C$2:$C$2000,"<="&DATE(2022,3,31)) -> 9 | V6: =COUNTIFS('Jump to Latest'!$C$2:$C$2000,">="&DATE(2021,10,1),'Jump to Latest'!$C$2:$C$2000,"<="&DATE(2021,12,31)) -> 1 | W6: =COUNTIFS('Jump to Latest'!$C$2:$C$2000,">="&DATE(2021,7,1),'Jump to Latest'!$C$2:$C$2000,"<="&DATE(2021,9,30)) -> 1 | X6: =COUNTIFS('Jump to Latest'!$C$2:$C$2000,">="&DATE(2021,4,1),'Jump to Latest'!$C$2:$C$2000,"<="&DATE(2021,6,30)) -> 2 | Y6: =COUNTIFS('Jump to Latest'!$C$2:$C$2000,">="&DATE(2021,1,1),'Jump to Latest'!$C$2:$C$2000,"<="&DATE(2021,3,31)) -> 1 | Z6: =COUNTIFS('Jump to Latest'!$C$2:$C$2000,">="&DATE(2020,10,1),'Jump to Latest'!$C$2:$C$2000,"<="&DATE(2020,12,31)) -> 0
A7: Thread navigation & message discovery | B7: Finding a specific message | C7: =COUNTIFS('Find Specific Message'!$C$2:$C$2000,">="&DATE(2026,7,1),'Find Specific Message'!$C$2:$C$2000,"<="&DATE(2026,9,30)) -> 1 | D7: =COUNTIFS('Find Specific Message'!$C$2:$C$2000,">="&DATE(2026,4,1),'Find Specific Message'!$C$2:$C$2000,"<="&DATE(2026,6,30)) -> 8 | E7: =COUNTIFS('Find Specific Message'!$C$2:$C$2000,">="&DATE(2026,1,1),'Find Specific Message'!$C$2:$C$2000,"<="&DATE(2026,3,31)) -> 2 | F7: =COUNTIFS('Find Specific Message'!$C$2:$C$2000,">="&DATE(2025,10,1),'Find Specific Message'!$C$2:$C$2000,"<="&DATE(2025,12,31)) -> 3 | G7: =COUNTIFS('Find Specific Message'!$C$2:$C$2000,">="&DATE(2025,7,1),'Find Specific Message'!$C$2:$C$2000,"<="&DATE(2025,9,30)) -> 3 | H7: =COUNTIFS('Find Specific Message'!$C$2:$C$2000,">="&DATE(2025,4,1),'Find Specific Message'!$C$2:$C$2000,"<="&DATE(2025,6,30)) -> 3 | I7: =COUNTIFS('Find Specific Message'!$C$2:$C$2000,">="&DATE(2025,1,1),'Find Specific Message'!$C$2:$C$2000,"<="&DATE(2025,3,31)) -> 5 | J7: =COUNTIFS('Find Specific Message'!$C$2:$C$2000,">="&DATE(2024,10,1),'Find Specific Message'!$C$2:$C$2000,"<="&DATE(2024,12,31)) -> 1 | K7: =COUNTIFS('Find Specific Message'!$C$2:$C$2000,">="&DATE(2024,7,1),'Find Specific Message'!$C$2:$C$2000,"<="&DATE(2024,9,30)) -> 3 | L7: =COUNTIFS('Find Specific Message'!$C$2:$C$2000,">="&DATE(2024,4,1),'Find Specific Message'!$C$2:$C$2000,"<="&DATE(2024,6,30)) -> 3 | M7: =COUNTIFS('Find Specific Message'!$C$2:$C$2000,">="&DATE(2024,1,1),'Find Specific Message'!$C$2:$C$2000,"<="&DATE(2024,3,31)) -> 3 | N7: =COUNTIFS('Find Specific Message'!$C$2:$C$2000,">="&DATE(2023,10,1),'Find Specific Message'!$C$2:$C$2000,"<="&DATE(2023,12,31)) -> 2 | O7: =COUNTIFS('Find Specific Message'!$C$2:$C$2000,">="&DATE(2023,7,1),'Find Specific Message'!$C$2:$C$2000,"<="&DATE(2023,9,30)) -> 2 | P7: =COUNTIFS('Find Specific Message'!$C$2:$C$2000,">="&DATE(2023,4,1),'Find Specific Message'!$C$2:$C$2000,"<="&DATE(2023,6,30)) -> 2 | Q7: =COUNTIFS('Find Specific Message'!$C$2:$C$2000,">="&DATE(2023,1,1),'Find Specific Message'!$C$2:$C$2000,"<="&DATE(2023,3,31)) -> 4 | R7: =COUNTIFS('Find Specific Message'!$C$2:$C$2000,">="&DATE(2022,10,1),'Find Specific Message'!$C$2:$C$2000,"<="&DATE(2022,12,31)) -> 1 | S7: =COUNTIFS('Find Specific Message'!$C$2:$C$2000,">="&DATE(2022,7,1),'Find Specific Message'!$C$2:$C$2000,"<="&DATE(2022,9,30)) -> 9 | T7: =COUNTIFS('Find Specific Message'!$C$2:$C$2000,">="&DATE(2022,4,1),'Find Specific Message'!$C$2:$C$2000,"<="&DATE(2022,6,30)) -> 9 | U7: =COUNTIFS('Find Specific Message'!$C$2:$C$2000,">="&DATE(2022,1,1),'Find Specific Message'!$C$2:$C$2000,"<="&DATE(2022,3,31)) -> 3 | V7: =COUNTIFS('Find Specific Message'!$C$2:$C$2000,">="&DATE(2021,10,1),'Find Specific Message'!$C$2:$C$2000,"<="&DATE(2021,12,31)) -> 5 | W7: =COUNTIFS('Find Specific Message'!$C$2:$C$2000,">="&DATE(2021,7,1),'Find Specific Message'!$C$2:$C$2000,"<="&DATE(2021,9,30)) -> 2 | X7: =COUNTIFS('Find Specific Message'!$C$2:$C$2000,">="&DATE(2021,4,1),'Find Specific Message'!$C$2:$C$2000,"<="&DATE(2021,6,30)) -> 4 | Y7: =COUNTIFS('Find Specific Message'!$C$2:$C$2000,">="&DATE(2021,1,1),'Find Specific Message'!$C$2:$C$2000,"<="&DATE(2021,3,31)) -> 1 | Z7: =COUNTIFS('Find Specific Message'!$C$2:$C$2000,">="&DATE(2020,10,1),'Find Specific Message'!$C$2:$C$2000,"<="&DATE(2020,12,31)) -> 1
A8: Thread navigation & message discovery | B8: Read/unread visibility | C8: =COUNTIFS('Read-Unread Visibility'!$C$2:$C$2000,">="&DATE(2026,7,1),'Read-Unread Visibility'!$C$2:$C$2000,"<="&DATE(2026,9,30)) -> 0 | D8: =COUNTIFS('Read-Unread Visibility'!$C$2:$C$2000,">="&DATE(2026,4,1),'Read-Unread Visibility'!$C$2:$C$2000,"<="&DATE(2026,6,30)) -> 0 | E8: =COUNTIFS('Read-Unread Visibility'!$C$2:$C$2000,">="&DATE(2026,1,1),'Read-Unread Visibility'!$C$2:$C$2000,"<="&DATE(2026,3,31)) -> 0 | F8: =COUNTIFS('Read-Unread Visibility'!$C$2:$C$2000,">="&DATE(2025,10,1),'Read-Unread Visibility'!$C$2:$C$2000,"<="&DATE(2025,12,31)) -> 0 | G8: =COUNTIFS('Read-Unread Visibility'!$C$2:$C$2000,">="&DATE(2025,7,1),'Read-Unread Visibility'!$C$2:$C$2000,"<="&DATE(2025,9,30)) -> 0 | H8: =COUNTIFS('Read-Unread Visibility'!$C$2:$C$2000,">="&DATE(2025,4,1),'Read-Unread Visibility'!$C$2:$C$2000,"<="&DATE(2025,6,30)) -> 0 | I8: =COUNTIFS('Read-Unread Visibility'!$C$2:$C$2000,">="&DATE(2025,1,1),'Read-Unread Visibility'!$C$2:$C$2000,"<="&DATE(2025,3,31)) -> 0 | J8: =COUNTIFS('Read-Unread Visibility'!$C$2:$C$2000,">="&DATE(2024,10,1),'Read-Unread Visibility'!$C$2:$C$2000,"<="&DATE(2024,12,31)) -> 0 | K8: =COUNTIFS('Read-Unread Visibility'!$C$2:$C$2000,">="&DATE(2024,7,1),'Read-Unread Visibility'!$C$2:$C$2000,"<="&DATE(2024,9,30)) -> 0 | L8: =COUNTIFS('Read-Unread Visibility'!$C$2:$C$2000,">="&DATE(2024,4,1),'Read-Unread Visibility'!$C$2:$C$2000,"<="&DATE(2024,6,30)) -> 0 | M8: =COUNTIFS('Read-Unread Visibility'!$C$2:$C$2000,">="&DATE(2024,1,1),'Read-Unread Visibility'!$C$2:$C$2000,"<="&DATE(2024,3,31)) -> 0 | N8: =COUNTIFS('Read-Unread Visibility'!$C$2:$C$2000,">="&DATE(2023,10,1),'Read-Unread Visibility'!$C$2:$C$2000,"<="&DATE(2023,12,31)) -> 0 | O8: =COUNTIFS('Read-Unread Visibility'!$C$2:$C$2000,">="&DATE(2023,7,1),'Read-Unread Visibility'!$C$2:$C$2000,"<="&DATE(2023,9,30)) -> 0 | P8: =COUNTIFS('Read-Unread Visibility'!$C$2:$C$2000,">="&DATE(2023,4,1),'Read-Unread Visibility'!$C$2:$C$2000,"<="&DATE(2023,6,30)) -> 0 | Q8: =COUNTIFS('Read-Unread Visibility'!$C$2:$C$2000,">="&DATE(2023,1,1),'Read-Unread Visibility'!$C$2:$C$2000,"<="&DATE(2023,3,31)) -> 0 | R8: =COUNTIFS('Read-Unread Visibility'!$C$2:$C$2000,">="&DATE(2022,10,1),'Read-Unread Visibility'!$C$2:$C$2000,"<="&DATE(2022,12,31)) -> 0 | S8: =COUNTIFS('Read-Unread Visibility'!$C$2:$C$2000,">="&DATE(2022,7,1),'Read-Unread Visibility'!$C$2:$C$2000,"<="&DATE(2022,9,30)) -> 0 | T8: =COUNTIFS('Read-Unread Visibility'!$C$2:$C$2000,">="&DATE(2022,4,1),'Read-Unread Visibility'!$C$2:$C$2000,"<="&DATE(2022,6,30)) -> 0 | U8: =COUNTIFS('Read-Unread Visibility'!$C$2:$C$2000,">="&DATE(2022,1,1),'Read-Unread Visibility'!$C$2:$C$2000,"<="&DATE(2022,3,31)) -> 0 | V8: =COUNTIFS('Read-Unread Visibility'!$C$2:$C$2000,">="&DATE(2021,10,1),'Read-Unread Visibility'!$C$2:$C$2000,"<="&DATE(2021,12,31)) -> 0 | W8: =COUNTIFS('Read-Unread Visibility'!$C$2:$C$2000,">="&DATE(2021,7,1),'Read-Unread Visibility'!$C$2:$C$2000,"<="&DATE(2021,9,30)) -> 0 | X8: =COUNTIFS('Read-Unread Visibility'!$C$2:$C$2000,">="&DATE(2021,4,1),'Read-Unread Visibility'!$C$2:$C$2000,"<="&DATE(2021,6,30)) -> 0 | Y8: =COUNTIFS('Read-Unread Visibility'!$C$2:$C$2000,">="&DATE(2021,1,1),'Read-Unread Visibility'!$C$2:$C$2000,"<="&DATE(2021,3,31)) -> 0 | Z8: =COUNTIFS('Read-Unread Visibility'!$C$2:$C$2000,">="&DATE(2020,10,1),'Read-Unread Visibility'!$C$2:$C$2000,"<="&DATE(2020,12,31)) -> 0
A9: Message actions | B9: Mark individual message unread | C9: =COUNTIFS('Mark Message Unread'!$C$2:$C$2000,">="&DATE(2026,7,1),'Mark Message Unread'!$C$2:$C$2000,"<="&DATE(2026,9,30)) -> 0 | D9: =COUNTIFS('Mark Message Unread'!$C$2:$C$2000,">="&DATE(2026,4,1),'Mark Message Unread'!$C$2:$C$2000,"<="&DATE(2026,6,30)) -> 0 | E9: =COUNTIFS('Mark Message Unread'!$C$2:$C$2000,">="&DATE(2026,1,1),'Mark Message Unread'!$C$2:$C$2000,"<="&DATE(2026,3,31)) -> 1 | F9: =COUNTIFS('Mark Message Unread'!$C$2:$C$2000,">="&DATE(2025,10,1),'Mark Message Unread'!$C$2:$C$2000,"<="&DATE(2025,12,31)) -> 1 | G9: =COUNTIFS('Mark Message Unread'!$C$2:$C$2000,">="&DATE(2025,7,1),'Mark Message Unread'!$C$2:$C$2000,"<="&DATE(2025,9,30)) -> 0 | H9: =COUNTIFS('Mark Message Unread'!$C$2:$C$2000,">="&DATE(2025,4,1),'Mark Message Unread'!$C$2:$C$2000,"<="&DATE(2025,6,30)) -> 0 | I9: =COUNTIFS('Mark Message Unread'!$C$2:$C$2000,">="&DATE(2025,1,1),'Mark Message Unread'!$C$2:$C$2000,"<="&DATE(2025,3,31)) -> 0 | J9: =COUNTIFS('Mark Message Unread'!$C$2:$C$2000,">="&DATE(2024,10,1),'Mark Message Unread'!$C$2:$C$2000,"<="&DATE(2024,12,31)) -> 0 | K9: =COUNTIFS('Mark Message Unread'!$C$2:$C$2000,">="&DATE(2024,7,1),'Mark Message Unread'!$C$2:$C$2000,"<="&DATE(2024,9,30)) -> 0 | L9: =COUNTIFS('Mark Message Unread'!$C$2:$C$2000,">="&DATE(2024,4,1),'Mark Message Unread'!$C$2:$C$2000,"<="&DATE(2024,6,30)) -> 0 | M9: =COUNTIFS('Mark Message Unread'!$C$2:$C$2000,">="&DATE(2024,1,1),'Mark Message Unread'!$C$2:$C$2000,"<="&DATE(2024,3,31)) -> 0 | N9: =COUNTIFS('Mark Message Unread'!$C$2:$C$2000,">="&DATE(2023,10,1),'Mark Message Unread'!$C$2:$C$2000,"<="&DATE(2023,12,31)) -> 0 | O9: =COUNTIFS('Mark Message Unread'!$C$2:$C$2000,">="&DATE(2023,7,1),'Mark Message Unread'!$C$2:$C$2000,"<="&DATE(2023,9,30)) -> 0 | P9: =COUNTIFS('Mark Message Unread'!$C$2:$C$2000,">="&DATE(2023,4,1),'Mark Message Unread'!$C$2:$C$2000,"<="&DATE(2023,6,30)) -> 0 | Q9: =COUNTIFS('Mark Message Unread'!$C$2:$C$2000,">="&DATE(2023,1,1),'Mark Message Unread'!$C$2:$C$2000,"<="&DATE(2023,3,31)) -> 0 | R9: =COUNTIFS('Mark Message Unread'!$C$2:$C$2000,">="&DATE(2022,10,1),'Mark Message Unread'!$C$2:$C$2000,"<="&DATE(2022,12,31)) -> 0 | S9: =COUNTIFS('Mark Message Unread'!$C$2:$C$2000,">="&DATE(2022,7,1),'Mark Message Unread'!$C$2:$C$2000,"<="&DATE(2022,9,30)) -> 1 | T9: =COUNTIFS('Mark Message Unread'!$C$2:$C$2000,">="&DATE(2022,4,1),'Mark Message Unread'!$C$2:$C$2000,"<="&DATE(2022,6,30)) -> 0 | U9: =COUNTIFS('Mark Message Unread'!$C$2:$C$2000,">="&DATE(2022,1,1),'Mark Message Unread'!$C$2:$C$2000,"<="&DATE(2022,3,31)) -> 0 | V9: =COUNTIFS('Mark Message Unread'!$C$2:$C$2000,">="&DATE(2021,10,1),'Mark Message Unread'!$C$2:$C$2000,"<="&DATE(2021,12,31)) -> 0 | W9: =COUNTIFS('Mark Message Unread'!$C$2:$C$2000,">="&DATE(2021,7,1),'Mark Message Unread'!$C$2:$C$2000,"<="&DATE(2021,9,30)) -> 0 | X9: =COUNTIFS('Mark Message Unread'!$C$2:$C$2000,">="&DATE(2021,4,1),'Mark Message Unread'!$C$2:$C$2000,"<="&DATE(2021,6,30)) -> 0 | Y9: =COUNTIFS('Mark Message Unread'!$C$2:$C$2000,">="&DATE(2021,1,1),'Mark Message Unread'!$C$2:$C$2000,"<="&DATE(2021,3,31)) -> 0 | Z9: =COUNTIFS('Mark Message Unread'!$C$2:$C$2000,">="&DATE(2020,10,1),'Mark Message Unread'!$C$2:$C$2000,"<="&DATE(2020,12,31)) -> 0
A10: Conversation grouping & boundaries | B10: Disable Conversation View | C10: =COUNTIFS('Disable Conversation'!$C$2:$C$2000,">="&DATE(2026,7,1),'Disable Conversation'!$C$2:$C$2000,"<="&DATE(2026,9,30)) -> 0 | D10: =COUNTIFS('Disable Conversation'!$C$2:$C$2000,">="&DATE(2026,4,1),'Disable Conversation'!$C$2:$C$2000,"<="&DATE(2026,6,30)) -> 4 | E10: =COUNTIFS('Disable Conversation'!$C$2:$C$2000,">="&DATE(2026,1,1),'Disable Conversation'!$C$2:$C$2000,"<="&DATE(2026,3,31)) -> 3 | F10: =COUNTIFS('Disable Conversation'!$C$2:$C$2000,">="&DATE(2025,10,1),'Disable Conversation'!$C$2:$C$2000,"<="&DATE(2025,12,31)) -> 1 | G10: =COUNTIFS('Disable Conversation'!$C$2:$C$2000,">="&DATE(2025,7,1),'Disable Conversation'!$C$2:$C$2000,"<="&DATE(2025,9,30)) -> 2 | H10: =COUNTIFS('Disable Conversation'!$C$2:$C$2000,">="&DATE(2025,4,1),'Disable Conversation'!$C$2:$C$2000,"<="&DATE(2025,6,30)) -> 5 | I10: =COUNTIFS('Disable Conversation'!$C$2:$C$2000,">="&DATE(2025,1,1),'Disable Conversation'!$C$2:$C$2000,"<="&DATE(2025,3,31)) -> 2 | J10: =COUNTIFS('Disable Conversation'!$C$2:$C$2000,">="&DATE(2024,10,1),'Disable Conversation'!$C$2:$C$2000,"<="&DATE(2024,12,31)) -> 4 | K10: =COUNTIFS('Disable Conversation'!$C$2:$C$2000,">="&DATE(2024,7,1),'Disable Conversation'!$C$2:$C$2000,"<="&DATE(2024,9,30)) -> 4 | L10: =COUNTIFS('Disable Conversation'!$C$2:$C$2000,">="&DATE(2024,4,1),'Disable Conversation'!$C$2:$C$2000,"<="&DATE(2024,6,30)) -> 4 | M10: =COUNTIFS('Disable Conversation'!$C$2:$C$2000,">="&DATE(2024,1,1),'Disable Conversation'!$C$2:$C$2000,"<="&DATE(2024,3,31)) -> 4 | N10: =COUNTIFS('Disable Conversation'!$C$2:$C$2000,">="&DATE(2023,10,1),'Disable Conversation'!$C$2:$C$2000,"<="&DATE(2023,12,31)) -> 6 | O10: =COUNTIFS('Disable Conversation'!$C$2:$C$2000,">="&DATE(2023,7,1),'Disable Conversation'!$C$2:$C$2000,"<="&DATE(2023,9,30)) -> 5 | P10: =COUNTIFS('Disable Conversation'!$C$2:$C$2000,">="&DATE(2023,4,1),'Disable Conversation'!$C$2:$C$2000,"<="&DATE(2023,6,30)) -> 8 | Q10: =COUNTIFS('Disable Conversation'!$C$2:$C$2000,">="&DATE(2023,1,1),'Disable Conversation'!$C$2:$C$2000,"<="&DATE(2023,3,31)) -> 12 | R10: =COUNTIFS('Disable Conversation'!$C$2:$C$2000,">="&DATE(2022,10,1),'Disable Conversation'!$C$2:$C$2000,"<="&DATE(2022,12,31)) -> 11 | S10: =COUNTIFS('Disable Conversation'!$C$2:$C$2000,">="&DATE(2022,7,1),'Disable Conversation'!$C$2:$C$2000,"<="&DATE(2022,9,30)) -> 29 | T10: =COUNTIFS('Disable Conversation'!$C$2:$C$2000,">="&DATE(2022,4,1),'Disable Conversation'!$C$2:$C$2000,"<="&DATE(2022,6,30)) -> 20 | U10: =COUNTIFS('Disable Conversation'!$C$2:$C$2000,">="&DATE(2022,1,1),'Disable Conversation'!$C$2:$C$2000,"<="&DATE(2022,3,31)) -> 18 | V10: =COUNTIFS('Disable Conversation'!$C$2:$C$2000,">="&DATE(2021,10,1),'Disable Conversation'!$C$2:$C$2000,"<="&DATE(2021,12,31)) -> 19 | W10: =COUNTIFS('Disable Conversation'!$C$2:$C$2000,">="&DATE(2021,7,1),'Disable Conversation'!$C$2:$C$2000,"<="&DATE(2021,9,30)) -> 15 | X10: =COUNTIFS('Disable Conversation'!$C$2:$C$2000,">="&DATE(2021,4,1),'Disable Conversation'!$C$2:$C$2000,"<="&DATE(2021,6,30)) -> 15 | Y10: =COUNTIFS('Disable Conversation'!$C$2:$C$2000,">="&DATE(2021,1,1),'Disable Conversation'!$C$2:$C$2000,"<="&DATE(2021,3,31)) -> 3 | Z10: =COUNTIFS('Disable Conversation'!$C$2:$C$2000,">="&DATE(2020,10,1),'Disable Conversation'!$C$2:$C$2000,"<="&DATE(2020,12,31)) -> 3
A11: Conversation grouping & boundaries | B11: Separate conversation branches | C11: =COUNTIFS('Separate Branches'!$C$2:$C$2000,">="&DATE(2026,7,1),'Separate Branches'!$C$2:$C$2000,"<="&DATE(2026,9,30)) -> 2 | D11: =COUNTIFS('Separate Branches'!$C$2:$C$2000,">="&DATE(2026,4,1),'Separate Branches'!$C$2:$C$2000,"<="&DATE(2026,6,30)) -> 2 | E11: =COUNTIFS('Separate Branches'!$C$2:$C$2000,">="&DATE(2026,1,1),'Separate Branches'!$C$2:$C$2000,"<="&DATE(2026,3,31)) -> 2 | F11: =COUNTIFS('Separate Branches'!$C$2:$C$2000,">="&DATE(2025,10,1),'Separate Branches'!$C$2:$C$2000,"<="&DATE(2025,12,31)) -> 1 | G11: =COUNTIFS('Separate Branches'!$C$2:$C$2000,">="&DATE(2025,7,1),'Separate Branches'!$C$2:$C$2000,"<="&DATE(2025,9,30)) -> 1 | H11: =COUNTIFS('Separate Branches'!$C$2:$C$2000,">="&DATE(2025,4,1),'Separate Branches'!$C$2:$C$2000,"<="&DATE(2025,6,30)) -> 1 | I11: =COUNTIFS('Separate Branches'!$C$2:$C$2000,">="&DATE(2025,1,1),'Separate Branches'!$C$2:$C$2000,"<="&DATE(2025,3,31)) -> 1 | J11: =COUNTIFS('Separate Branches'!$C$2:$C$2000,">="&DATE(2024,10,1),'Separate Branches'!$C$2:$C$2000,"<="&DATE(2024,12,31)) -> 1 | K11: =COUNTIFS('Separate Branches'!$C$2:$C$2000,">="&DATE(2024,7,1),'Separate Branches'!$C$2:$C$2000,"<="&DATE(2024,9,30)) -> 1 | L11: =COUNTIFS('Separate Branches'!$C$2:$C$2000,">="&DATE(2024,4,1),'Separate Branches'!$C$2:$C$2000,"<="&DATE(2024,6,30)) -> 0 | M11: =COUNTIFS('Separate Branches'!$C$2:$C$2000,">="&DATE(2024,1,1),'Separate Branches'!$C$2:$C$2000,"<="&DATE(2024,3,31)) -> 1 | N11: =COUNTIFS('Separate Branches'!$C$2:$C$2000,">="&DATE(2023,10,1),'Separate Branches'!$C$2:$C$2000,"<="&DATE(2023,12,31)) -> 0 | O11: =COUNTIFS('Separate Branches'!$C$2:$C$2000,">="&DATE(2023,7,1),'Separate Branches'!$C$2:$C$2000,"<="&DATE(2023,9,30)) -> 1 | P11: =COUNTIFS('Separate Branches'!$C$2:$C$2000,">="&DATE(2023,4,1),'Separate Branches'!$C$2:$C$2000,"<="&DATE(2023,6,30)) -> 0 | Q11: =COUNTIFS('Separate Branches'!$C$2:$C$2000,">="&DATE(2023,1,1),'Separate Branches'!$C$2:$C$2000,"<="&DATE(2023,3,31)) -> 0 | R11: =COUNTIFS('Separate Branches'!$C$2:$C$2000,">="&DATE(2022,10,1),'Separate Branches'!$C$2:$C$2000,"<="&DATE(2022,12,31)) -> 1 | S11: =COUNTIFS('Separate Branches'!$C$2:$C$2000,">="&DATE(2022,7,1),'Separate Branches'!$C$2:$C$2000,"<="&DATE(2022,9,30)) -> 0 | T11: =COUNTIFS('Separate Branches'!$C$2:$C$2000,">="&DATE(2022,4,1),'Separate Branches'!$C$2:$C$2000,"<="&DATE(2022,6,30)) -> 2 | U11: =COUNTIFS('Separate Branches'!$C$2:$C$2000,">="&DATE(2022,1,1),'Separate Branches'!$C$2:$C$2000,"<="&DATE(2022,3,31)) -> 2 | V11: =COUNTIFS('Separate Branches'!$C$2:$C$2000,">="&DATE(2021,10,1),'Separate Branches'!$C$2:$C$2000,"<="&DATE(2021,12,31)) -> 0 | W11: =COUNTIFS('Separate Branches'!$C$2:$C$2000,">="&DATE(2021,7,1),'Separate Branches'!$C$2:$C$2000,"<="&DATE(2021,9,30)) -> 1 | X11: =COUNTIFS('Separate Branches'!$C$2:$C$2000,">="&DATE(2021,4,1),'Separate Branches'!$C$2:$C$2000,"<="&DATE(2021,6,30)) -> 1 | Y11: =COUNTIFS('Separate Branches'!$C$2:$C$2000,">="&DATE(2021,1,1),'Separate Branches'!$C$2:$C$2000,"<="&DATE(2021,3,31)) -> 2 | Z11: =COUNTIFS('Separate Branches'!$C$2:$C$2000,">="&DATE(2020,10,1),'Separate Branches'!$C$2:$C$2000,"<="&DATE(2020,12,31)) -> 0
A12: Thread readability & structure | B12: Nested / quoted content readability | C12: =COUNTIFS('Quoted Readability'!$C$2:$C$2000,">="&DATE(2026,7,1),'Quoted Readability'!$C$2:$C$2000,"<="&DATE(2026,9,30)) -> 2 | D12: =COUNTIFS('Quoted Readability'!$C$2:$C$2000,">="&DATE(2026,4,1),'Quoted Readability'!$C$2:$C$2000,"<="&DATE(2026,6,30)) -> 2 | E12: =COUNTIFS('Quoted Readability'!$C$2:$C$2000,">="&DATE(2026,1,1),'Quoted Readability'!$C$2:$C$2000,"<="&DATE(2026,3,31)) -> 1 | F12: =COUNTIFS('Quoted Readability'!$C$2:$C$2000,">="&DATE(2025,10,1),'Quoted Readability'!$C$2:$C$2000,"<="&DATE(2025,12,31)) -> 0 | G12: =COUNTIFS('Quoted Readability'!$C$2:$C$2000,">="&DATE(2025,7,1),'Quoted Readability'!$C$2:$C$2000,"<="&DATE(2025,9,30)) -> 0 | H12: =COUNTIFS('Quoted Readability'!$C$2:$C$2000,">="&DATE(2025,4,1),'Quoted Readability'!$C$2:$C$2000,"<="&DATE(2025,6,30)) -> 0 | I12: =COUNTIFS('Quoted Readability'!$C$2:$C$2000,">="&DATE(2025,1,1),'Quoted Readability'!$C$2:$C$2000,"<="&DATE(2025,3,31)) -> 1 | J12: =COUNTIFS('Quoted Readability'!$C$2:$C$2000,">="&DATE(2024,10,1),'Quoted Readability'!$C$2:$C$2000,"<="&DATE(2024,12,31)) -> 0 | K12: =COUNTIFS('Quoted Readability'!$C$2:$C$2000,">="&DATE(2024,7,1),'Quoted Readability'!$C$2:$C$2000,"<="&DATE(2024,9,30)) -> 0 | L12: =COUNTIFS('Quoted Readability'!$C$2:$C$2000,">="&DATE(2024,4,1),'Quoted Readability'!$C$2:$C$2000,"<="&DATE(2024,6,30)) -> 0 | M12: =COUNTIFS('Quoted Readability'!$C$2:$C$2000,">="&DATE(2024,1,1),'Quoted Readability'!$C$2:$C$2000,"<="&DATE(2024,3,31)) -> 2 | N12: =COUNTIFS('Quoted Readability'!$C$2:$C$2000,">="&DATE(2023,10,1),'Quoted Readability'!$C$2:$C$2000,"<="&DATE(2023,12,31)) -> 0 | O12: =COUNTIFS('Quoted Readability'!$C$2:$C$2000,">="&DATE(2023,7,1),'Quoted Readability'!$C$2:$C$2000,"<="&DATE(2023,9,30)) -> 0 | P12: =COUNTIFS('Quoted Readability'!$C$2:$C$2000,">="&DATE(2023,4,1),'Quoted Readability'!$C$2:$C$2000,"<="&DATE(2023,6,30)) -> 0 | Q12: =COUNTIFS('Quoted Readability'!$C$2:$C$2000,">="&DATE(2023,1,1),'Quoted Readability'!$C$2:$C$2000,"<="&DATE(2023,3,31)) -> 0 | R12: =COUNTIFS('Quoted Readability'!$C$2:$C$2000,">="&DATE(2022,10,1),'Quoted Readability'!$C$2:$C$2000,"<="&DATE(2022,12,31)) -> 0 | S12: =COUNTIFS('Quoted Readability'!$C$2:$C$2000,">="&DATE(2022,7,1),'Quoted Readability'!$C$2:$C$2000,"<="&DATE(2022,9,30)) -> 0 | T12: =COUNTIFS('Quoted Readability'!$C$2:$C$2000,">="&DATE(2022,4,1),'Quoted Readability'!$C$2:$C$2000,"<="&DATE(2022,6,30)) -> 1 | U12: =COUNTIFS('Quoted Readability'!$C$2:$C$2000,">="&DATE(2022,1,1),'Quoted Readability'!$C$2:$C$2000,"<="&DATE(2022,3,31)) -> 0 | V12: =COUNTIFS('Quoted Readability'!$C$2:$C$2000,">="&DATE(2021,10,1),'Quoted Readability'!$C$2:$C$2000,"<="&DATE(2021,12,31)) -> 0 | W12: =COUNTIFS('Quoted Readability'!$C$2:$C$2000,">="&DATE(2021,7,1),'Quoted Readability'!$C$2:$C$2000,"<="&DATE(2021,9,30)) -> 0 | X12: =COUNTIFS('Quoted Readability'!$C$2:$C$2000,">="&DATE(2021,4,1),'Quoted Readability'!$C$2:$C$2000,"<="&DATE(2021,6,30)) -> 0 | Y12: =COUNTIFS('Quoted Readability'!$C$2:$C$2000,">="&DATE(2021,1,1),'Quoted Readability'!$C$2:$C$2000,"<="&DATE(2021,3,31)) -> 0 | Z12: =COUNTIFS('Quoted Readability'!$C$2:$C$2000,">="&DATE(2020,10,1),'Quoted Readability'!$C$2:$C$2000,"<="&DATE(2020,12,31)) -> 0
A13: Attachments in threads | B13: Attachment discovery & access | C13: =COUNTIFS('Attachment Discovery'!$C$2:$C$2000,">="&DATE(2026,7,1),'Attachment Discovery'!$C$2:$C$2000,"<="&DATE(2026,9,30)) -> 0 | D13: =COUNTIFS('Attachment Discovery'!$C$2:$C$2000,">="&DATE(2026,4,1),'Attachment Discovery'!$C$2:$C$2000,"<="&DATE(2026,6,30)) -> 4 | E13: =COUNTIFS('Attachment Discovery'!$C$2:$C$2000,">="&DATE(2026,1,1),'Attachment Discovery'!$C$2:$C$2000,"<="&DATE(2026,3,31)) -> 1 | F13: =COUNTIFS('Attachment Discovery'!$C$2:$C$2000,">="&DATE(2025,10,1),'Attachment Discovery'!$C$2:$C$2000,"<="&DATE(2025,12,31)) -> 1 | G13: =COUNTIFS('Attachment Discovery'!$C$2:$C$2000,">="&DATE(2025,7,1),'Attachment Discovery'!$C$2:$C$2000,"<="&DATE(2025,9,30)) -> 2 | H13: =COUNTIFS('Attachment Discovery'!$C$2:$C$2000,">="&DATE(2025,4,1),'Attachment Discovery'!$C$2:$C$2000,"<="&DATE(2025,6,30)) -> 1 | I13: =COUNTIFS('Attachment Discovery'!$C$2:$C$2000,">="&DATE(2025,1,1),'Attachment Discovery'!$C$2:$C$2000,"<="&DATE(2025,3,31)) -> 1 | J13: =COUNTIFS('Attachment Discovery'!$C$2:$C$2000,">="&DATE(2024,10,1),'Attachment Discovery'!$C$2:$C$2000,"<="&DATE(2024,12,31)) -> 1 | K13: =COUNTIFS('Attachment Discovery'!$C$2:$C$2000,">="&DATE(2024,7,1),'Attachment Discovery'!$C$2:$C$2000,"<="&DATE(2024,9,30)) -> 0 | L13: =COUNTIFS('Attachment Discovery'!$C$2:$C$2000,">="&DATE(2024,4,1),'Attachment Discovery'!$C$2:$C$2000,"<="&DATE(2024,6,30)) -> 2 | M13: =COUNTIFS('Attachment Discovery'!$C$2:$C$2000,">="&DATE(2024,1,1),'Attachment Discovery'!$C$2:$C$2000,"<="&DATE(2024,3,31)) -> 2 | N13: =COUNTIFS('Attachment Discovery'!$C$2:$C$2000,">="&DATE(2023,10,1),'Attachment Discovery'!$C$2:$C$2000,"<="&DATE(2023,12,31)) -> 1 | O13: =COUNTIFS('Attachment Discovery'!$C$2:$C$2000,">="&DATE(2023,7,1),'Attachment Discovery'!$C$2:$C$2000,"<="&DATE(2023,9,30)) -> 2 | P13: =COUNTIFS('Attachment Discovery'!$C$2:$C$2000,">="&DATE(2023,4,1),'Attachment Discovery'!$C$2:$C$2000,"<="&DATE(2023,6,30)) -> 0 | Q13: =COUNTIFS('Attachment Discovery'!$C$2:$C$2000,">="&DATE(2023,1,1),'Attachment Discovery'!$C$2:$C$2000,"<="&DATE(2023,3,31)) -> 3 | R13: =COUNTIFS('Attachment Discovery'!$C$2:$C$2000,">="&DATE(2022,10,1),'Attachment Discovery'!$C$2:$C$2000,"<="&DATE(2022,12,31)) -> 1 | S13: =COUNTIFS('Attachment Discovery'!$C$2:$C$2000,">="&DATE(2022,7,1),'Attachment Discovery'!$C$2:$C$2000,"<="&DATE(2022,9,30)) -> 3 | T13: =COUNTIFS('Attachment Discovery'!$C$2:$C$2000,">="&DATE(2022,4,1),'Attachment Discovery'!$C$2:$C$2000,"<="&DATE(2022,6,30)) -> 2 | U13: =COUNTIFS('Attachment Discovery'!$C$2:$C$2000,">="&DATE(2022,1,1),'Attachment Discovery'!$C$2:$C$2000,"<="&DATE(2022,3,31)) -> 1 | V13: =COUNTIFS('Attachment Discovery'!$C$2:$C$2000,">="&DATE(2021,10,1),'Attachment Discovery'!$C$2:$C$2000,"<="&DATE(2021,12,31)) -> 0 | W13: =COUNTIFS('Attachment Discovery'!$C$2:$C$2000,">="&DATE(2021,7,1),'Attachment Discovery'!$C$2:$C$2000,"<="&DATE(2021,9,30)) -> 0 | X13: =COUNTIFS('Attachment Discovery'!$C$2:$C$2000,">="&DATE(2021,4,1),'Attachment Discovery'!$C$2:$C$2000,"<="&DATE(2021,6,30)) -> 0 | Y13: =COUNTIFS('Attachment Discovery'!$C$2:$C$2000,">="&DATE(2021,1,1),'Attachment Discovery'!$C$2:$C$2000,"<="&DATE(2021,3,31)) -> 1 | Z13: =COUNTIFS('Attachment Discovery'!$C$2:$C$2000,">="&DATE(2020,10,1),'Attachment Discovery'!$C$2:$C$2000,"<="&DATE(2020,12,31)) -> 0
A14: Attachments in threads | B14: Attachment carry-over | C14: =COUNTIFS('Attachment Carry-over'!$C$2:$C$2000,">="&DATE(2026,7,1),'Attachment Carry-over'!$C$2:$C$2000,"<="&DATE(2026,9,30)) -> 0 | D14: =COUNTIFS('Attachment Carry-over'!$C$2:$C$2000,">="&DATE(2026,4,1),'Attachment Carry-over'!$C$2:$C$2000,"<="&DATE(2026,6,30)) -> 0 | E14: =COUNTIFS('Attachment Carry-over'!$C$2:$C$2000,">="&DATE(2026,1,1),'Attachment Carry-over'!$C$2:$C$2000,"<="&DATE(2026,3,31)) -> 0 | F14: =COUNTIFS('Attachment Carry-over'!$C$2:$C$2000,">="&DATE(2025,10,1),'Attachment Carry-over'!$C$2:$C$2000,"<="&DATE(2025,12,31)) -> 0 | G14: =COUNTIFS('Attachment Carry-over'!$C$2:$C$2000,">="&DATE(2025,7,1),'Attachment Carry-over'!$C$2:$C$2000,"<="&DATE(2025,9,30)) -> 0 | H14: =COUNTIFS('Attachment Carry-over'!$C$2:$C$2000,">="&DATE(2025,4,1),'Attachment Carry-over'!$C$2:$C$2000,"<="&DATE(2025,6,30)) -> 0 | I14: =COUNTIFS('Attachment Carry-over'!$C$2:$C$2000,">="&DATE(2025,1,1),'Attachment Carry-over'!$C$2:$C$2000,"<="&DATE(2025,3,31)) -> 1 | J14: =COUNTIFS('Attachment Carry-over'!$C$2:$C$2000,">="&DATE(2024,10,1),'Attachment Carry-over'!$C$2:$C$2000,"<="&DATE(2024,12,31)) -> 0 | K14: =COUNTIFS('Attachment Carry-over'!$C$2:$C$2000,">="&DATE(2024,7,1),'Attachment Carry-over'!$C$2:$C$2000,"<="&DATE(2024,9,30)) -> 0 | L14: =COUNTIFS('Attachment Carry-over'!$C$2:$C$2000,">="&DATE(2024,4,1),'Attachment Carry-over'!$C$2:$C$2000,"<="&DATE(2024,6,30)) -> 0 | M14: =COUNTIFS('Attachment Carry-over'!$C$2:$C$2000,">="&DATE(2024,1,1),'Attachment Carry-over'!$C$2:$C$2000,"<="&DATE(2024,3,31)) -> 0 | N14: =COUNTIFS('Attachment Carry-over'!$C$2:$C$2000,">="&DATE(2023,10,1),'Attachment Carry-over'!$C$2:$C$2000,"<="&DATE(2023,12,31)) -> 0 | O14: =COUNTIFS('Attachment Carry-over'!$C$2:$C$2000,">="&DATE(2023,7,1),'Attachment Carry-over'!$C$2:$C$2000,"<="&DATE(2023,9,30)) -> 0 | P14: =COUNTIFS('Attachment Carry-over'!$C$2:$C$2000,">="&DATE(2023,4,1),'Attachment Carry-over'!$C$2:$C$2000,"<="&DATE(2023,6,30)) -> 0 | Q14: =COUNTIFS('Attachment Carry-over'!$C$2:$C$2000,">="&DATE(2023,1,1),'Attachment Carry-over'!$C$2:$C$2000,"<="&DATE(2023,3,31)) -> 0 | R14: =COUNTIFS('Attachment Carry-over'!$C$2:$C$2000,">="&DATE(2022,10,1),'Attachment Carry-over'!$C$2:$C$2000,"<="&DATE(2022,12,31)) -> 0 | S14: =COUNTIFS('Attachment Carry-over'!$C$2:$C$2000,">="&DATE(2022,7,1),'Attachment Carry-over'!$C$2:$C$2000,"<="&DATE(2022,9,30)) -> 0 | T14: =COUNTIFS('Attachment Carry-over'!$C$2:$C$2000,">="&DATE(2022,4,1),'Attachment Carry-over'!$C$2:$C$2000,"<="&DATE(2022,6,30)) -> 0 | U14: =COUNTIFS('Attachment Carry-over'!$C$2:$C$2000,">="&DATE(2022,1,1),'Attachment Carry-over'!$C$2:$C$2000,"<="&DATE(2022,3,31)) -> 0 | V14: =COUNTIFS('Attachment Carry-over'!$C$2:$C$2000,">="&DATE(2021,10,1),'Attachment Carry-over'!$C$2:$C$2000,"<="&DATE(2021,12,31)) -> 0 | W14: =COUNTIFS('Attachment Carry-over'!$C$2:$C$2000,">="&DATE(2021,7,1),'Attachment Carry-over'!$C$2:$C$2000,"<="&DATE(2021,9,30)) -> 0 | X14: =COUNTIFS('Attachment Carry-over'!$C$2:$C$2000,">="&DATE(2021,4,1),'Attachment Carry-over'!$C$2:$C$2000,"<="&DATE(2021,6,30)) -> 0 | Y14: =COUNTIFS('Attachment Carry-over'!$C$2:$C$2000,">="&DATE(2021,1,1),'Attachment Carry-over'!$C$2:$C$2000,"<="&DATE(2021,3,31)) -> 0 | Z14: =COUNTIFS('Attachment Carry-over'!$C$2:$C$2000,">="&DATE(2020,10,1),'Attachment Carry-over'!$C$2:$C$2000,"<="&DATE(2020,12,31)) -> 0
A15: Thread reliability | B15: Message rendering | C15: =COUNTIFS('Message Rendering'!$C$2:$C$2000,">="&DATE(2026,7,1),'Message Rendering'!$C$2:$C$2000,"<="&DATE(2026,9,30)) -> 1 | D15: =COUNTIFS('Message Rendering'!$C$2:$C$2000,">="&DATE(2026,4,1),'Message Rendering'!$C$2:$C$2000,"<="&DATE(2026,6,30)) -> 3 | E15: =COUNTIFS('Message Rendering'!$C$2:$C$2000,">="&DATE(2026,1,1),'Message Rendering'!$C$2:$C$2000,"<="&DATE(2026,3,31)) -> 2 | F15: =COUNTIFS('Message Rendering'!$C$2:$C$2000,">="&DATE(2025,10,1),'Message Rendering'!$C$2:$C$2000,"<="&DATE(2025,12,31)) -> 1 | G15: =COUNTIFS('Message Rendering'!$C$2:$C$2000,">="&DATE(2025,7,1),'Message Rendering'!$C$2:$C$2000,"<="&DATE(2025,9,30)) -> 1 | H15: =COUNTIFS('Message Rendering'!$C$2:$C$2000,">="&DATE(2025,4,1),'Message Rendering'!$C$2:$C$2000,"<="&DATE(2025,6,30)) -> 1 | I15: =COUNTIFS('Message Rendering'!$C$2:$C$2000,">="&DATE(2025,1,1),'Message Rendering'!$C$2:$C$2000,"<="&DATE(2025,3,31)) -> 3 | J15: =COUNTIFS('Message Rendering'!$C$2:$C$2000,">="&DATE(2024,10,1),'Message Rendering'!$C$2:$C$2000,"<="&DATE(2024,12,31)) -> 0 | K15: =COUNTIFS('Message Rendering'!$C$2:$C$2000,">="&DATE(2024,7,1),'Message Rendering'!$C$2:$C$2000,"<="&DATE(2024,9,30)) -> 1 | L15: =COUNTIFS('Message Rendering'!$C$2:$C$2000,">="&DATE(2024,4,1),'Message Rendering'!$C$2:$C$2000,"<="&DATE(2024,6,30)) -> 2 | M15: =COUNTIFS('Message Rendering'!$C$2:$C$2000,">="&DATE(2024,1,1),'Message Rendering'!$C$2:$C$2000,"<="&DATE(2024,3,31)) -> 2 | N15: =COUNTIFS('Message Rendering'!$C$2:$C$2000,">="&DATE(2023,10,1),'Message Rendering'!$C$2:$C$2000,"<="&DATE(2023,12,31)) -> 1 | O15: =COUNTIFS('Message Rendering'!$C$2:$C$2000,">="&DATE(2023,7,1),'Message Rendering'!$C$2:$C$2000,"<="&DATE(2023,9,30)) -> 1 | P15: =COUNTIFS('Message Rendering'!$C$2:$C$2000,">="&DATE(2023,4,1),'Message Rendering'!$C$2:$C$2000,"<="&DATE(2023,6,30)) -> 4 | Q15: =COUNTIFS('Message Rendering'!$C$2:$C$2000,">="&DATE(2023,1,1),'Message Rendering'!$C$2:$C$2000,"<="&DATE(2023,3,31)) -> 2 | R15: =COUNTIFS('Message Rendering'!$C$2:$C$2000,">="&DATE(2022,10,1),'Message Rendering'!$C$2:$C$2000,"<="&DATE(2022,12,31)) -> 0 | S15: =COUNTIFS('Message Rendering'!$C$2:$C$2000,">="&DATE(2022,7,1),'Message Rendering'!$C$2:$C$2000,"<="&DATE(2022,9,30)) -> 1 | T15: =COUNTIFS('Message Rendering'!$C$2:$C$2000,">="&DATE(2022,4,1),'Message Rendering'!$C$2:$C$2000,"<="&DATE(2022,6,30)) -> 1 | U15: =COUNTIFS('Message Rendering'!$C$2:$C$2000,">="&DATE(2022,1,1),'Message Rendering'!$C$2:$C$2000,"<="&DATE(2022,3,31)) -> 2 | V15: =COUNTIFS('Message Rendering'!$C$2:$C$2000,">="&DATE(2021,10,1),'Message Rendering'!$C$2:$C$2000,"<="&DATE(2021,12,31)) -> 0 | W15: =COUNTIFS('Message Rendering'!$C$2:$C$2000,">="&DATE(2021,7,1),'Message Rendering'!$C$2:$C$2000,"<="&DATE(2021,9,30)) -> 0 | X15: =COUNTIFS('Message Rendering'!$C$2:$C$2000,">="&DATE(2021,4,1),'Message Rendering'!$C$2:$C$2000,"<="&DATE(2021,6,30)) -> 0 | Y15: =COUNTIFS('Message Rendering'!$C$2:$C$2000,">="&DATE(2021,1,1),'Message Rendering'!$C$2:$C$2000,"<="&DATE(2021,3,31)) -> 0 | Z15: =COUNTIFS('Message Rendering'!$C$2:$C$2000,">="&DATE(2020,10,1),'Message Rendering'!$C$2:$C$2000,"<="&DATE(2020,12,31)) -> 0
A16: Thread sharing | B16: Attach conversation to a new email | C16: =COUNTIFS('Attach Conversation'!$C$2:$C$2000,">="&DATE(2026,7,1),'Attach Conversation'!$C$2:$C$2000,"<="&DATE(2026,9,30)) -> 1 | D16: =COUNTIFS('Attach Conversation'!$C$2:$C$2000,">="&DATE(2026,4,1),'Attach Conversation'!$C$2:$C$2000,"<="&DATE(2026,6,30)) -> 1 | E16: =COUNTIFS('Attach Conversation'!$C$2:$C$2000,">="&DATE(2026,1,1),'Attach Conversation'!$C$2:$C$2000,"<="&DATE(2026,3,31)) -> 0 | F16: =COUNTIFS('Attach Conversation'!$C$2:$C$2000,">="&DATE(2025,10,1),'Attach Conversation'!$C$2:$C$2000,"<="&DATE(2025,12,31)) -> 0 | G16: =COUNTIFS('Attach Conversation'!$C$2:$C$2000,">="&DATE(2025,7,1),'Attach Conversation'!$C$2:$C$2000,"<="&DATE(2025,9,30)) -> 0 | H16: =COUNTIFS('Attach Conversation'!$C$2:$C$2000,">="&DATE(2025,4,1),'Attach Conversation'!$C$2:$C$2000,"<="&DATE(2025,6,30)) -> 0 | I16: =COUNTIFS('Attach Conversation'!$C$2:$C$2000,">="&DATE(2025,1,1),'Attach Conversation'!$C$2:$C$2000,"<="&DATE(2025,3,31)) -> 0 | J16: =COUNTIFS('Attach Conversation'!$C$2:$C$2000,">="&DATE(2024,10,1),'Attach Conversation'!$C$2:$C$2000,"<="&DATE(2024,12,31)) -> 0 | K16: =COUNTIFS('Attach Conversation'!$C$2:$C$2000,">="&DATE(2024,7,1),'Attach Conversation'!$C$2:$C$2000,"<="&DATE(2024,9,30)) -> 0 | L16: =COUNTIFS('Attach Conversation'!$C$2:$C$2000,">="&DATE(2024,4,1),'Attach Conversation'!$C$2:$C$2000,"<="&DATE(2024,6,30)) -> 0 | M16: =COUNTIFS('Attach Conversation'!$C$2:$C$2000,">="&DATE(2024,1,1),'Attach Conversation'!$C$2:$C$2000,"<="&DATE(2024,3,31)) -> 0 | N16: =COUNTIFS('Attach Conversation'!$C$2:$C$2000,">="&DATE(2023,10,1),'Attach Conversation'!$C$2:$C$2000,"<="&DATE(2023,12,31)) -> 0 | O16: =COUNTIFS('Attach Conversation'!$C$2:$C$2000,">="&DATE(2023,7,1),'Attach Conversation'!$C$2:$C$2000,"<="&DATE(2023,9,30)) -> 0 | P16: =COUNTIFS('Attach Conversation'!$C$2:$C$2000,">="&DATE(2023,4,1),'Attach Conversation'!$C$2:$C$2000,"<="&DATE(2023,6,30)) -> 0 | Q16: =COUNTIFS('Attach Conversation'!$C$2:$C$2000,">="&DATE(2023,1,1),'Attach Conversation'!$C$2:$C$2000,"<="&DATE(2023,3,31)) -> 0 | R16: =COUNTIFS('Attach Conversation'!$C$2:$C$2000,">="&DATE(2022,10,1),'Attach Conversation'!$C$2:$C$2000,"<="&DATE(2022,12,31)) -> 0 | S16: =COUNTIFS('Attach Conversation'!$C$2:$C$2000,">="&DATE(2022,7,1),'Attach Conversation'!$C$2:$C$2000,"<="&DATE(2022,9,30)) -> 0 | T16: =COUNTIFS('Attach Conversation'!$C$2:$C$2000,">="&DATE(2022,4,1),'Attach Conversation'!$C$2:$C$2000,"<="&DATE(2022,6,30)) -> 0 | U16: =COUNTIFS('Attach Conversation'!$C$2:$C$2000,">="&DATE(2022,1,1),'Attach Conversation'!$C$2:$C$2000,"<="&DATE(2022,3,31)) -> 0 | V16: =COUNTIFS('Attach Conversation'!$C$2:$C$2000,">="&DATE(2021,10,1),'Attach Conversation'!$C$2:$C$2000,"<="&DATE(2021,12,31)) -> 0 | W16: =COUNTIFS('Attach Conversation'!$C$2:$C$2000,">="&DATE(2021,7,1),'Attach Conversation'!$C$2:$C$2000,"<="&DATE(2021,9,30)) -> 0 | X16: =COUNTIFS('Attach Conversation'!$C$2:$C$2000,">="&DATE(2021,4,1),'Attach Conversation'!$C$2:$C$2000,"<="&DATE(2021,6,30)) -> 0 | Y16: =COUNTIFS('Attach Conversation'!$C$2:$C$2000,">="&DATE(2021,1,1),'Attach Conversation'!$C$2:$C$2000,"<="&DATE(2021,3,31)) -> 0 | Z16: =COUNTIFS('Attach Conversation'!$C$2:$C$2000,">="&DATE(2020,10,1),'Attach Conversation'!$C$2:$C$2000,"<="&DATE(2020,12,31)) -> 0
A17: Thread sharing | B17: Print full conversation | C17: =COUNTIFS('Print Conversation'!$C$2:$C$2000,">="&DATE(2026,7,1),'Print Conversation'!$C$2:$C$2000,"<="&DATE(2026,9,30)) -> 0 | D17: =COUNTIFS('Print Conversation'!$C$2:$C$2000,">="&DATE(2026,4,1),'Print Conversation'!$C$2:$C$2000,"<="&DATE(2026,6,30)) -> 0 | E17: =COUNTIFS('Print Conversation'!$C$2:$C$2000,">="&DATE(2026,1,1),'Print Conversation'!$C$2:$C$2000,"<="&DATE(2026,3,31)) -> 0 | F17: =COUNTIFS('Print Conversation'!$C$2:$C$2000,">="&DATE(2025,10,1),'Print Conversation'!$C$2:$C$2000,"<="&DATE(2025,12,31)) -> 1 | G17: =COUNTIFS('Print Conversation'!$C$2:$C$2000,">="&DATE(2025,7,1),'Print Conversation'!$C$2:$C$2000,"<="&DATE(2025,9,30)) -> 0 | H17: =COUNTIFS('Print Conversation'!$C$2:$C$2000,">="&DATE(2025,4,1),'Print Conversation'!$C$2:$C$2000,"<="&DATE(2025,6,30)) -> 0 | I17: =COUNTIFS('Print Conversation'!$C$2:$C$2000,">="&DATE(2025,1,1),'Print Conversation'!$C$2:$C$2000,"<="&DATE(2025,3,31)) -> 0 | J17: =COUNTIFS('Print Conversation'!$C$2:$C$2000,">="&DATE(2024,10,1),'Print Conversation'!$C$2:$C$2000,"<="&DATE(2024,12,31)) -> 1 | K17: =COUNTIFS('Print Conversation'!$C$2:$C$2000,">="&DATE(2024,7,1),'Print Conversation'!$C$2:$C$2000,"<="&DATE(2024,9,30)) -> 0 | L17: =COUNTIFS('Print Conversation'!$C$2:$C$2000,">="&DATE(2024,4,1),'Print Conversation'!$C$2:$C$2000,"<="&DATE(2024,6,30)) -> 0 | M17: =COUNTIFS('Print Conversation'!$C$2:$C$2000,">="&DATE(2024,1,1),'Print Conversation'!$C$2:$C$2000,"<="&DATE(2024,3,31)) -> 1 | N17: =COUNTIFS('Print Conversation'!$C$2:$C$2000,">="&DATE(2023,10,1),'Print Conversation'!$C$2:$C$2000,"<="&DATE(2023,12,31)) -> 0 | O17: =COUNTIFS('Print Conversation'!$C$2:$C$2000,">="&DATE(2023,7,1),'Print Conversation'!$C$2:$C$2000,"<="&DATE(2023,9,30)) -> 0 | P17: =COUNTIFS('Print Conversation'!$C$2:$C$2000,">="&DATE(2023,4,1),'Print Conversation'!$C$2:$C$2000,"<="&DATE(2023,6,30)) -> 0 | Q17: =COUNTIFS('Print Conversation'!$C$2:$C$2000,">="&DATE(2023,1,1),'Print Conversation'!$C$2:$C$2000,"<="&DATE(2023,3,31)) -> 0 | R17: =COUNTIFS('Print Conversation'!$C$2:$C$2000,">="&DATE(2022,10,1),'Print Conversation'!$C$2:$C$2000,"<="&DATE(2022,12,31)) -> 1 | S17: =COUNTIFS('Print Conversation'!$C$2:$C$2000,">="&DATE(2022,7,1),'Print Conversation'!$C$2:$C$2000,"<="&DATE(2022,9,30)) -> 0 | T17: =COUNTIFS('Print Conversation'!$C$2:$C$2000,">="&DATE(2022,4,1),'Print Conversation'!$C$2:$C$2000,"<="&DATE(2022,6,30)) -> 1 | U17: =COUNTIFS('Print Conversation'!$C$2:$C$2000,">="&DATE(2022,1,1),'Print Conversation'!$C$2:$C$2000,"<="&DATE(2022,3,31)) -> 0 | V17: =COUNTIFS('Print Conversation'!$C$2:$C$2000,">="&DATE(2021,10,1),'Print Conversation'!$C$2:$C$2000,"<="&DATE(2021,12,31)) -> 0 | W17: =COUNTIFS('Print Conversation'!$C$2:$C$2000,">="&DATE(2021,7,1),'Print Conversation'!$C$2:$C$2000,"<="&DATE(2021,9,30)) -> 2 | X17: =COUNTIFS('Print Conversation'!$C$2:$C$2000,">="&DATE(2021,4,1),'Print Conversation'!$C$2:$C$2000,"<="&DATE(2021,6,30)) -> 1 | Y17: =COUNTIFS('Print Conversation'!$C$2:$C$2000,">="&DATE(2021,1,1),'Print Conversation'!$C$2:$C$2000,"<="&DATE(2021,3,31)) -> 1 | Z17: =COUNTIFS('Print Conversation'!$C$2:$C$2000,">="&DATE(2020,10,1),'Print Conversation'!$C$2:$C$2000,"<="&DATE(2020,12,31)) -> 0
B18: Total | C18: =SUM(C5:C17) -> 13 | D18: =SUM(D5:D17) -> 36 | E18: =SUM(E5:E17) -> 19 | F18: =SUM(F5:F17) -> 17 | G18: =SUM(G5:G17) -> 16 | H18: =SUM(H5:H17) -> 18 | I18: =SUM(I5:I17) -> 20 | J18: =SUM(J5:J17) -> 13 | ... Z18: =SUM(Z5:Z17) -> 4

Sheet Unclassified Feedback
A1: Account ID | B1: Feedback Date | C1: NPS Score | D1: Plan | E1: Partner | F1: Source | G1: Feedback | H1: Reason Not Classified
A2: 10000114 | B2: 46252 | C2: 2 | D2: Pro | E2: Bluehost | F2: NPS | G2: The mobile app is brutal. Trying to review all of the emails in a thread takes forever. I frequently have to go back to the desktop browser to get the emails to load. [Improvement: Fix that] | H2: Issue lies outside Conversation View (search, delivery, deletion, compose, performance, etc.).
A3: 10836957 | B3: 46250 | C3: 8 | D3: Pro | E3: Secureserver | F3: NPS | G3: some times it is confusing to follow conversations in the same thread [Improvement: find a way to separate reply and follow up mails] | H3: Complaint or request too vague to identify which underlying thread problem is meant.
A4: 9983249 | B4: 46244 | C4: 10 | D4: Pro | E4: Secureserver | F4: NPS | G4: The layout and feel is better than Outlook, Yes 1 change i would request is Mail trail needs to be seperated. | H4: Complaint or request too vague to identify which underlying thread problem is meant.
A5: 8999462 | B5: 46238 | C5: 9 | D5: Pro | E5: Vodien | F5: NPS | G5: Easy to use. However, it can be even better if it has an AI feature to collate an email thread to summarize the contents of the thread discussion. | H5: Describes a real thread-related need, but it does not map to any predefined sub-theme.
A6: 10822667 | B6: 46237 | C6: 1 | D6: Ultra | E6: Secureserver | F6: NPS | G6: The way that email threads is organised is terrible. [Improvement: email thread organisation.] | H6: Generic complaint about thread usability; no specific underlying problem identifiable.
A7: 10997771 | B7: 46231 | C7: 7 | D7: Free | E7: Hostinger | F7: NPS | G7: The way the emails get stacked and displayed is confusing and doesn't follow the same process as gmail or other mainstream mail providers which causes time delays and is inefficient. [Improvement: Make the email chains easier to follow. Either follow the process Gmail and others use or be inventive and make it even better.] | H7: Generic complaint about thread usability; no specific underlying problem identifiable.
A8: 3105126 | B8: 46227 | C8: 4 | D8: Premium | E8: name.com | F8: NPS | G8: Threads are extremely unwieldy. | H8: Generic complaint about thread usability; no specific underlying problem identifiable.
A9: 7134577 | B9: 46226 | C9: 6 | D9: Pro | E9: WordPress.com | F9: NPS | G9: The email layout is not clean enough. Too costly for what you offer. Nothing special. I do not like the way the reply emails stack up. Confusing and not easily overseeable. [Improvement: See my comments. Make it cleaner.] | H9: Generic complaint about thread usability; no specific underlying problem identifiable.
A10: 5348995 | B10: 46222 | C10: 6 | D10: Free | E10: Hostinger | F10: NPS | G10: Blocking emails should not be a paid feature. With the high amount of spam, that seems like something everyone should have automatically. [Improvement: Make blocking free... Make it easier to find threads and copy email addresses] | H10: Issue lies outside Conversation View (search, delivery, deletion, compose, performance, etc.).
A11: 7881668 | B11: 46216 | C11: 10 | D11: Starter | E11: ResellerClub Newfold | F11: NPS | G11: I have had no difficulty; the email history is visible right away, so there is no need to go to Sent to check. | H11: Positive or neutral feedback; no problem described.
A12: 10239683 | B12: 46211 | C12: 1 | D12: Pro | E12: Secureserver | F12: NPS | G12: All confusing previous GoDaddy version was easy to understand and use. [Improvement: All mails in thread collapsing, causing confusion. Make things easier instead of charging for AI] | H12: Complaint or request too vague to identify which underlying thread problem is meant.
A13: 8645714 | B13: 46203 | C13: 3 | D13: Free | E13: Hostinger | F13: NPS | G13: Keeps asking me to upgrade for this and upgrade for that. Cant search properly, as all e-mails are nested into one, etc | H13: Issue lies outside Conversation View (search, delivery, deletion, compose, performance, etc.).
... A298: 132202 | B298: 44118 | C298: 2 | D298: Free | E298: TSO Host | F298: NPS | G298: nothing is easy. you cant right click to copy. its really hard to keep track of the threads. cant see my old sent emails. i really liked my old Mr Site email it was simple and very good | H298: Generic complaint about thread usability; no specific underlying problem identifiable.

Sheet Message Ordering
A1: Classification Clarity | B1: Account ID | C1: Feedback Date | D1: NPS Score | E1: Plan | F1: Partner | G1: Source | H1: Highlighted Relevant Comment | I1: Full Feedback
A2: Very clear | B2: 3980890 | C2: 46246 | D2: 9 | E2: Pro | F2: WordPress.com | G2: NPS | H2: sometimes the email thread chain is backwards when reading emails in order | I2: sometimes the email thread chain is backwards when reading emails in order [Improvement: order this please x]
A3: Very clear | B3: 5197887 | C3: 46245 | D3: 1 | E3: Pro | F3: Hostinger | G3: NPS | H3: there is no flow in the message. top to bottom. new message comes in the middle instead | I3: there is no flow in the message. top to bottom. new message comes in the middle instead
A4: Very clear | B4: 10819108 | C4: 46217 | D4: 3 | E4: Pro | F4: Secureserver | G4: NPS | H4: Mixed up of old and new mails | I4: Email thread too complicated! Mixed up of old and new mails! Need effort to search the latest mail!
A5: Very clear | B5: 8273859 | C5: 46191 | D5: 5 | E5: Free | F5: HostGator | G5: NPS | H5: the latest reply appearing in the middle of that history | I5: The organisation of the email is poor. It is bad that the email history always shows up, with the latest reply appearing in the middle of that history. It is very confusing. And an email that should only appear in Sent also appears in the inbox. [Improvement: Give the option not to show the email history. And sent is sent... it should not appear anywhere else.]
A6: Very clear | B6: 6848029 | C6: 46183 | D6: 3 | E6: Free | F6: Hostinger | G6: NPS | H6: thread of messages do not follow on in received order | I6: Stacking of emails not logical , they become disorganised and thread of messages do not follow on in received order . A real pain.
A7: Very clear | B7: 9166325 | C7: 46146 | D7: 1 | E7: Pro | F7: Secureserver | G7: NPS | H7: the latest response pops up in the middle | I7: piece of crap, lags, and doesnt attach things properly. the order of messages is confusing in a 50 reply message thread its confusing, the latest response pops up in the middle, you gotta scroll up and down to find past replies but its ten not in order. put things in a linear order, newest reponse coming up as you click, and you can scroll back in chronological order with all attachments under each response. at the moment this is a piece of crap [Improvement: i just told you]
A8: Very clear | B8: 6703977 | C8: 46121 | D8: 6 | E8: Pro | F8: Hostgator Chile | G8: NPS | H8: sometimes the last one sent ends up in the middle of the emails or at the end and does not follow a logical, ordered sequence | I8: It is very cumbersome and unfriendly with the views. It does NOT allow panels to be hidden, and it is unclear when it joins together emails from the same series that are sent... Everything gets tangled. [Improvement: The way it joins emails from a series is bad; sometimes the last one sent ends up in the middle of the emails or at the end and does not follow a logical, ordered sequence. The image formatting also gets lost.]
A9: Very clear | B9: 1487682 | C9: 46079 | D9: 2 | E9: Premium | F9: TSO Host | G9: NPS | H9: Conversation threads are difficult to follow as they appear out of order | I9: Conversation threads are difficult to follow as they appear out of order.
A10: Very clear | B10: 8176083 | C10: 46063 | D10: 8 | E10: Pro | F10: WordPress.com | G10: NPS | H10: the sequence or order gets lost | I10: It is excellent, but I find that in email threads under the same subject the sequence or order gets lost, and it is hard to find the last one.
A11: Very clear | B11: 3974113 | C11: 46045 | D11: 6 | E11: Premium | F11: HostGator | G11: NPS | H11: The message history within a single email is messy. Ideally it should follow a bottom-to-top sequence | I11: The message history within a single email is messy. Ideally it should follow a bottom-to-top sequence. This message-exchange dynamic is not practical.
A12: Very clear | B12: 6848029 | C12: 46010 | D12: 6 | E12: Free | F12: Hostinger | G12: NPS | H12: they don't seem to stay in date order | I12: Chain of emails difficult to navigate as they don't seem to stay in date order and sometimes appear twice .
A13: Very clear | B13: 3105126 | C13: 45954 | D13: 3 | E13: Premium | F13: name.com | G13: NPS | H13: Once there's more than a few emails in a chain, they are out of order | I13: Threads are impossible. Once there's more than a few emails in a chain, they are out of order. Just model the flow after Gmail. [Improvement: See previous note.]
... A95: Moderate | B95: 280387 | C95: 44519 | D95: 7 | E95: Pro | F95: WordPress.com | G95: NPS | H95: I do not like the system for opening email threads, it looks very disordered | I95: Because it is fine but I do not like the system for opening email threads, it looks very disordered.

Sheet Jump to Latest
A1: Classification Clarity | B1: Account ID | C1: Feedback Date | D1: NPS Score | E1: Plan | F1: Partner | G1: Source | H1: Highlighted Relevant Comment | I1: Full Feedback
A2: Very clear | B2: 10819108 | C2: 46217 | D2: 3 | E2: Pro | F2: Secureserver | G2: NPS | H2: Need effort to search the latest mail | I2: Email thread too complicated! Mixed up of old and new mails! Need effort to search the latest mail!
A3: Very clear | B3: 10662219 | C3: 46203 | D3: 7 | E3: Pro | F3: Crazy Domains | G3: NPS | H3: very hard to se the most recent message | I3: Its not perfect by any means [Improvement: Threading of messages is very confussing on Mobile particularily, very hard to se the most recent message. The read receipts function I don't want and apparently am not subscribed to but still the creepy eye symbol taunts me with notifications of people having opened my emails...but it is of zero value as I can't see who has anyway and don't want to..so take the whole feature away please!!!]
A4: Very clear | B4: 10482078 | C4: 46178 | D4: 4 | E4: Ultra | F4: Hostinger | G4: NPS | H4: I struggle to figure out what the latest email is | I4: 1) Cannot build tables without being able to do HTML coding. 2) No native Windows client... No offline access to email. 3) Android client... sometimes email font is way too small to read and cannot zoom in. 4) I cannot right click or double-click any name in To, CC, BCC to get the actual email address. 5) Something is odd about when in Conversation mode. I can't put my finger on it but, I struggle to figure out what the latest email is. 6) Challenge where WebApp via Chrome reduces double/triple spaces to single space. 7) Challenge where emojis I add in the WebApp via Chrome turn into pictures. [Improvement: see last page. #1 a Windows app.]
A5: Very clear | B5: 4866745 | C5: 46150 | D5: 6 | E5: Pro | F5: Hostinger | G5: NPS | H5: in a trailed email, it is very hard to find the last one that came in | I5: in a trailed email, it is very hard to find the last one that came in. Also I cannot add "importance" to an email that I am sending out. Not sure why this is not in the basic package. [Improvement: Is there any training sessions to show us what is included in the package I have so I see if I want to upgrade?]
A6: Very clear | B6: 3257959 | C6: 46133 | D6: 7 | E6: Premium | F6: name.com | G6: NPS | H6: It's difficult to keep track of latest messages | I6: It's read confirmation is good. Grammatical correction while typing is good. However the way it keeps email messages io thread is not good. It's difficult to keep track of latest messages. [Improvement: Better management of email threads. Grouping all messages under one subject is good.. yet we need to track any new message. Some emails go unnoticed.]
A7: Very clear | B7: 7980726 | C7: 46100 | D7: 7 | E7: Pro | F7: WordPress.com | G7: NPS | H7: I have to scroll through allthe past emails to find the latest one | I7: It gets a little confusing how the emails from one person gets grouped. When I go to open the latest one, it seems I have to scroll through allthe past emails to find the latest one. I like that they are grouped it just gets confusing which is the latest one when I go to open the newest email.
A8: Very clear | B8: 4147646 | C8: 46076 | D8: 3 | E8: Free | F8: Hostinger | G8: NPS | H8: The UI when reading chain emails is hard to navigate to the latest message | I8: All of the random fee's and complicated tier pricing. Charging for signature blocks, really? The UI when reading chain emails is hard to navigate to the latest message. It is worth a couple more dollars to use MS Outlook [Improvement: Flatten the tiers and simplify the pricing.]
A9: Very clear | B9: 8176083 | C9: 46063 | D9: 8 | E9: Pro | F9: WordPress.com | G9: NPS | H9: it is hard to find the last one | I9: It is excellent, but I find that in email threads under the same subject the sequence or order gets lost, and it is hard to find the last one.
A10: Very clear | B10: 7979778 | C10: 45996 | D10: 6 | E10: Pro | F10: Secureserver | G10: NPS | H10: It's always difficult to find the last one | I10: Visualisation of mail groups is not convenient, not well readable. It's always difficult to find the last one. it would be good to have a newest on top not on the bottom.
A11: Very clear | B11: 4561677 | C11: 45872 | D11: 8 | E11: Pro | F11: Hostinger | G11: NPS | H11: titan doesnot show me the most recent email instead I have to search it in the trailing emails | I11: The only problem I have is, titan doesnot show me the most recent email instead I have to search it in the trailing emails.
A12: Very clear | B12: 6590209 | C12: 45841 | D12: 7 | E12: Premium | F12: Vodien | G12: NPS | H12: makes it hard to find a new message amongst a chain of emails | I12: The system is functional but it is over-engineered; grouping messages in conversations sometimes makes it hard to find a new message amongst a chain of emails
A13: Very clear | B13: 2180678 | C13: 45814 | D13: 8 | E13: Pro | F13: WordPress.com | G13: NPS | H13: Sometimes hard to find the most recent email | I13: Overall a good email system. It takes a little getting used to to have the conversations arranged as email threads go on. Sometimes hard to find the most recent email. I come from Yahoo, so may just be me.
... A70: Moderate | B70: 222151 | C70: 44663 | D70: 6 | E70: Pro | F70: Hostinger | G70: NPS | H70: Presentation of latest email in a long chain | I70: Sometimes find it difficult to find an email when there is a long chain of replies [Improvement: Presentation of latest email in a long chain]

Sheet Find Specific Message
A1: Classification Clarity | B1: Account ID | C1: Feedback Date | D1: NPS Score | E1: Plan | F1: Partner | G1: Source | H1: Highlighted Relevant Comment | I1: Full Feedback
A2: Very clear | B2: 10767743 | C2: 46223 | D2: 4 | E2: Pro Plus | F2: Secureserver | G2: NPS | H2: it is more of a struggle to find a specific one by the date it was sent | I2: The change they made to the email was not good. It is much slower, emails from the same user get grouped, and it is more of a struggle to find a specific one by the date it was sent.
A3: Very clear | B3: 3374249 | C3: 46072 | D3: 7 | E3: Premium | F3: Hostgator Mexico | G3: NPS | H3: they pile up and it is hard to find an email within the thread | I3: The email thread interface is not very friendly; they pile up and it is hard to find an email within the thread. They should be more independent, the way Outlook does it. [Improvement: Make the interface friendlier]
A4: Very clear | B4: 6659778 | C4: 46006 | D4: 3 | E4: Free | F4: Hostinger | G4: NPS | H4: very difficult to find individual; emails in a thread | I4: the way that the system 'stacks' emails is irritating making it very difficult to find individual; emails in a thread
A5: Very clear | B5: 6764087 | C5: 45964 | D5: 3 | E5: Pro | F5: WordPress.com | G5: NPS | H5: I find it difficult to locate previous emails, particularly when they are in an email thread | I5: I find it difficult to locate previous emails, particularly when they are in an email thread
A6: Very clear | B6: 3836964 | C6: 45884 | D6: 1 | E6: Pro | F6: WordPress.com | G6: NPS | H6: It takes an age to find a particular email | I6: I HATE the way conversations are nested. It takes an age to find a particular email, and deleting one email deletes the entire thread.
A7: Very clear | B7: 3207667 | C7: 45870 | D7: 7 | E7: Pro | F7: WordPress.com | G7: NPS | H7: difficult to find specific messages among a thread of multiple messages | I7: difficult to find specific messages among a thread of multiple messages.
A8: Very clear | B8: 2004685 | C8: 45601 | D8: 7 | E8: Pro | F8: WordPress.com | G8: NPS | H8: It's hard trying to find emails within threads | I8: It's hard trying to find emails within threads, which causes me real headaches. But so does Gmail - neither of you do it as clearly as Outlook. But otherwise, Titan is pretty good and integrates with my web domain without me having to pay extra for Outlook. [Improvement: Stop clumping email threads together. I want all my emails as separate "letters" in my inbox, otherwise I can't find stuff.]
A9: Very clear | B9: 5041221 | C9: 45446 | D9: 6 | E9: Premium | F9: Hostinger | G9: NPS | H9: Searching for old e-mail in an e-mail trail is abit hectic | I9: Searching for old e-mail in an e-mail trail is abit hectic [Improvement: Make it more user friendly]
A10: Very clear | B10: 4641609 | C10: 45436 | D10: 8 | E10: Pro | F10: WordPress.com | G10: NPS | H10: hard to find a specific email once it has been replied to. I have to search through a string of messages | I10: I've received a few spam emails appearing to be from Titan support, and now I don't know when I'm really communicating with support. Also, it is sometimes hard to find a specific email once it has been replied to. I have to search through a string of messages. [Improvement: I'm not sure, maybe I can set the email conversations to display differently.]
A11: Very clear | B11: 1722574 | C11: 45413 | D11: 8 | E11: Pro | F11: WordPress.com | G11: NPS | H11: it is often not easy to locate an email in a multiple email thread | I11: I would have given a 10 because my overall experience has been good, however, I don't like the fact that it is often not easy to locate an email in a multiple email thread. [Improvement: Arrange individual emails in a thread with multiple emails in chronological order.]
A12: Very clear | B12: 2438639 | C12: 45034 | D12: 7 | E12: Free | F12: Hostgator Mexico | G12: NPS | H12: I always have to keep clicking each email until I find what I am looking for within the thread | I12: I still do not understand the basic functions of the mail reader, and I have not explored them. I find it hard to see the email thread and I always have to keep clicking each email until I find what I am looking for within the thread. [Improvement: Put the basic functions in view so they can be changed in one click]
A13: Very clear | B13: 235355 | C13: 44904 | D13: 1 | E13: Pro | F13: WordPress.com | G13: NPS | H13: difficult to find emails within email threads | I13: difficult to find emails within email threads. difficult to integrate with outlook.
... A81: Moderate | B81: 106273 | C81: 44131 | D81: 1 | E81: Free | F81: TSO Host | G81: NPS | H81: I can't find emails very easily | I81: There are too many bad points to this email service - I don't like how the conversations are grouped and I can't find emails very easily. Wish we had never moved over to this email. [Improvement: needs a complete refurb and changes]

Sheet Read-Unread Visibility
A1: Classification Clarity | B1: Account ID | C1: Feedback Date | D1: NPS Score | E1: Plan | F1: Partner | G1: Source | H1: Highlighted Relevant Comment | I1: Full Feedback

Sheet Mark Message Unread
A1: Classification Clarity | B1: Account ID | C1: Feedback Date | D1: NPS Score | E1: Plan | F1: Partner | G1: Source | H1: Highlighted Relevant Comment | I1: Full Feedback
A2: Very clear | B2: 1348064 | C2: 44763 | D2: 7 | E2: Premium | F2: Hostinger | G2: NPS | H2: Mark individual emails unread rather than full threads | I2: Solid, clean and reliable email UI. Somewhat light on features that I'm used to from Gmail. [Improvement: Mark individual emails unread rather than full threads. Designate/flag emails that come to me from mailing lists.]
A3: Clear | B3: 6764889 | C3: 46062 | D3: 5 | E3: Pro | F3: WordPress.com | G3: NPS | H3: you can mark just one email as unread from a thread | I3: On iphone the search for a particular email sometimes doesnt work properly. Also, you can mark just one email as unread from a thread.
A4: Clear | B4: 6712333 | C4: 45986 | D4: 6 | E4: Premium | F4: HostGator US | G4: NPS | H4: I would like to be able to mark a read email as new | I4: I would like to be able to mark a read email as new; so that I can get back to it by easily seeing it as bold. The email chains are difficult to deal with when some emails are above and some below when reading the latest. If one forwards an email to someone else, it should not then be part of the old email chain.

Sheet Disable Conversation
A1: Classification Clarity | B1: Account ID | C1: Feedback Date | D1: NPS Score | E1: Plan | F1: Partner | G1: Source | H1: Highlighted Relevant Comment | I1: Full Feedback
A2: Very clear | B2: 9235848 | C2: 46148 | D2: 1 | E2: Free | F2: Hostinger | G2: NPS | H2: You cannot change email from conversation view to single email view | I2: It is a paid version, yet you get too many upgrade prompts. You cannot change email from conversation view to single email view. Sometimes, it is difficulty to pick the mail to reply from a long history of the same email thread [Improvement: Fix the issues.]
A3: Very clear | B3: 216696 | C3: 46132 | D3: 9 | E3: Premium | F3: Hostinger | G3: NPS | H3: Provide an options where emails do not need to be grouped by thread, but can be separated into their own email | I3: Good service, good price. [Improvement: Provide an options where emails do not need to be grouped by thread, but can be separated into their own email]
A4: Very clear | B4: 7956637 | C4: 46104 | D4: 3 | E4: Free | F4: Hostinger | G4: NPS | H4: I cant change from conversation mode to single email | I4: Free means bare minimum, emails I file show back up in the inbox, I cant change from conversation mode to single email. And to be constantly bombarded by popups telling me to upgrade. All very annoying, wish I didn't have to use this app. [Improvement: read previous message]
A5: Very clear | B5: 6784354 | C5: 45949 | D5: 3 | E5: Free | F5: Hostinger | G5: NPS | H5: better if each is shown individually on screen according to date and time | I5: you bundle all emails into one zipped email, its very difficult to figure out individual email, often leading to respond to incorrect email. better if each is shown individually on screen according to date and time. [Improvement: keep the emails in inbox and outbox as per time and date of email instead of zipped up into one]
A6: Very clear | B6: 6780550 | C6: 45867 | D6: 8 | E6: Premium | F6: HostGator | G6: NPS | H6: the lack of an option to show individual emails instead of grouped by conversation | I6: Almost perfect, except for the lack of an option to show individual emails instead of grouped by conversation.
A7: Very clear | B7: 1817441 | C7: 45845 | D7: 2 | E7: Pro | F7: WordPress.com | G7: NPS | H7: dont tie email threads together | I7: Dont like hot it ties email threads, prefer to keep them sperate! done not always user friendly!!! [Improvement: dont tie email threads together. make more user friendly]
A8: Very clear | B8: 6481236 | C8: 45762 | D8: 10 | E8: Premium | F8: Rumahweb | G8: NPS | H8: The email sequence can be set to stand alone without having to be combined into one continuous email | I8: Because it really helps me in communicating with correct writing rules. [Improvement: The email sequence can be set to stand alone without having to be combined into one continuous email. Because sometimes it becomes confusing and difficult to find one email that is needed.]
A9: Very clear | B9: 6367789 | C9: 45705 | D9: 10 | E9: Pro | F9: WordPress.com | G9: NPS | H9: I'd prefer it, if just one email opened instead of the entire string of emails | I9: I feel that its very safe and enjoy the way it seamlessly connects to my cellphone, so I never miss a notification. [Improvement: I'd prefer it, if just one email opened instead of the entire string of emails, however that could be something in the settings I have messed up.]
A10: Very clear | B10: 217144 | C10: 45602 | D10: 10 | E10: Pro | F10: Hostinger | G10: NPS | H10: Don't join up email chains | I10: Its better than others [Improvement: Don't join up email chains]
A11: Very clear | B11: 2004685 | C11: 45601 | D11: 7 | E11: Pro | F11: WordPress.com | G11: NPS | H11: Stop clumping email threads together. I want all my emails as separate "letters" in my inbox | I11: It's hard trying to find emails within threads, which causes me real headaches. But so does Gmail - neither of you do it as clearly as Outlook. But otherwise, Titan is pretty good and integrates with my web domain without me having to pay extra for Outlook. [Improvement: Stop clumping email threads together. I want all my emails as separate "letters" in my inbox, otherwise I can't find stuff.]
A12: Very clear | B12: 3491152 | C12: 45569 | D12: 10 | E12: Pro | F12: Zyro | G12: NPS | H12: Please create a version of not thread | I12: I am satisfied with the speed of loading and convenient to know if the emails I sent was opened or not. I would like to have a choice of interface if I like thread style to show or not. I am confused all the time when I reply to emails, because my own replied emails(or forwared) are always shown and I do not know where I am now in the conversation. I hate it. [Improvement: Please create a version of not thread.]
A13: Very clear | B13: 1014717 | C13: 45560 | D13: 6 | E13: Pro | F13: WordPress.com | G13: NPS | H13: it is very annoying to have to see the whole email thread and not just the original | I13: I do not like not being able to see an original email on its own; it is very annoying to have to see the whole email thread and not just the original. Also very annoying not being able to delete a draft I do not need. [Improvement: By making it less like Gmail.]
... A198: Moderate | B198: 203969 | C198: 44367 | D198: 1 | E198: Pro | F198: TSO Host | G198: NPS | H198: I hate conversation view | I198: I hate conversation view

Sheet Separate Branches
A1: Classification Clarity | B1: Account ID | C1: Feedback Date | D1: NPS Score | E1: Plan | F1: Partner | G1: Source | H1: Highlighted Relevant Comment | I1: Full Feedback
A2: Very clear | B2: 5589048 | C2: 46105 | D2: 5 | E2: Premium | F2: HostGator | G2: NPS | H2: it mixes the conversations with other email addresses | I2: When messages have the same subject they join together and become a mess, because sometimes they are the same subject and it mixes the conversations with other email addresses.
A3: Very clear | B3: 6755629 | C3: 46060 | D3: 5 | E3: Premium | F3: HostGator | G3: NPS | H3: It groups emails and histories under the same subject; the recipients are sometimes different | I3: It groups emails and histories under the same subject; the recipients are sometimes different, which is not practical at all and gets confusing.
A4: Very clear | B4: 6712333 | C4: 45986 | D4: 6 | E4: Premium | F4: HostGator US | G4: NPS | H4: If one forwards an email to someone else, it should not then be part of the old email chain | I4: I would like to be able to mark a read email as new; so that I can get back to it by easily seeing it as bold. The email chains are difficult to deal with when some emails are above and some below when reading the latest. If one forwards an email to someone else, it should not then be part of the old email chain.
A5: Very clear | B5: 6792736 | C5: 45860 | D5: 4 | E5: Pro | F5: WordPress.com | G5: NPS | H5: When I respond to someone new I'd like for a new email thread to be started | I5: When I respond to someone new I'd like for a new email thread to be started. Now it's very complex to properly follow along.
A6: Very clear | B6: 3726421 | C6: 45724 | D6: 3 | E6: Pro | F6: Hostinger | G6: NPS | H6: they are grouped under one even I change recipients in responding emails | I6: Emails I want to see separate, but they are grouped under one even I change recipients in responding emails. [Improvement: add more advanced functions tools available in gmail app]
A7: Very clear | B7: 5506443 | C7: 45642 | D7: 8 | E7: Pro | F7: WordPress.com | G7: NPS | H7: It is very difficult to manage responses to e-mails that were forwarded to a new recipient. Than all the answers get put together | I7: Good email with one topic to improve: It is very difficult to manage responses to e-mails that were forwarded to a new recipient. Than all the answers get put together and it is so difficult to separate and follow the threads....
A8: Very clear | B8: 3758111 | C8: 45530 | D8: 8 | E8: Pro | F8: Hostinger | G8: NPS | H8: When you forward an email and change the subject, it does not create a new email thread; it stays in the same email list | I8: Managing different accounts and profiles. [Improvement: When you forward an email and change the subject, it does not create a new email thread; it stays in the same email list.]
A9: Very clear | B9: 3516928 | C9: 45334 | D9: 3 | E9: Premium | F9: Hostinger | G9: NPS | H9: Threads don't change when I change the subject line making things confusing | I9: Email is very convoluted and not easy to sort through. Threads don't change when I change the subject line making things confusing [Improvement: streamlined emails or a way to import into Gmail or other email service of my choice]
A10: Very clear | B10: 2498527 | C10: 45117 | D10: 1 | E10: Free | F10: Hostgator Mexico | G10: NPS | H10: IT PUTS EMAILS INTO THE THREAD THAT DO NOT BELONG | I10: IT PUTS EMAILS INTO THE THREAD THAT DO NOT BELONG, CAUSING CONFUSION IN FOLLOWING THEM. STORAGE CAPACITY IS VERY LOW COMPARED TO GMAIL OR HOTMAIL
A11: Very clear | B11: 1120955 | C11: 44695 | D11: 5 | E11: Pro | F11: WordPress.com | G11: NPS | H11: clients get lumped together when sending invoices, or receiving replies from invoices, and you can't separate them manually | I11: I wish the thread weren't grouped as a chat - especially when regarding similar topics. Often times, clients get lumped together when sending invoices, or receiving replies from invoices, and you can't separate them manually. [Improvement: see note]
A12: Very clear | B12: 234359 | C12: 44565 | D12: 4 | E12: Pro | F12: WordPress.com | G12: NPS | H12: especially if it's the same subject but different recipients | I12: Email chains are organised in a very confusing manner, especially if it's the same subject but different recipients. Very difficult to find and manage emails [Improvement: change how email chains are organised (do the same as outlook)]
A13: Very clear | B13: 239825 | C13: 44269 | D13: 7 | E13: Pro | F13: Hostinger | G13: NPS | H13: separating forwarded messages from the original thread | I13: A few things on the mobile app could be improved. [Improvement: separating forwarded messages from the original thread. possibility of checking who opened the email on the mobile app]
... A24: Moderate | B24: 116024 | C24: 44259 | D24: 1 | E24: Pro | F24: Hostinger | G24: NPS | H24: you have multiple chains of conversations going in the same section | I24: The email flow is extremely confusing. I can never tell if i'm responding to the correct email or not because you have multiple chains of conversations going in the same section. It should be sent>response>sent>response etc. [Improvement: Fix everything i just discussed]

Sheet Quoted Readability
A1: Classification Clarity | B1: Account ID | C1: Feedback Date | D1: NPS Score | E1: Plan | F1: Partner | G1: Source | H1: Highlighted Relevant Comment | I1: Full Feedback
A2: Very clear | B2: 648473 | C2: 46189 | D2: 4 | E2: Pro | F2: WordPress.com | G2: NPS | H2: Reading through a quoted email thread that you weren't part of is practically impossible | I2: So many inconveniences that add unnecessary friction to my work day. Reading through a quoted email thread that you weren't part of is practically impossible. No translate function. You can't mark emails as unread on the mobile app. That's just off the top of my head right now. There are many more reasons. [Improvement: Fix the types of problems I just mentioned.]
A3: Very clear | B3: 7914516 | C3: 46153 | D3: 1 | E3: Pro | F3: HostGator | G3: NPS | H3: the email history makes it harder to check the messages because they keep "shrinking" towards the right-hand side | I3: Emails cannot be forwarded in full, and the email history makes it harder to check the messages because they keep "shrinking" towards the right-hand side. I think it is very bad.
A4: Very clear | B4: 6362442 | C4: 45688 | D4: 5 | E4: Premium | F4: BigRock | G4: NPS | H4: older email in same conversation shrinks when we forward the email to outside titan | I4: the web interface is laggy while typing emails compare to gmail mail editor, make it smooth while typing. email threads should be like outlook and not like gmail, I have already submitted suggestion on this point. [Improvement: 1) email threads should look like outlook and not like gmail as older email in same conversation shrinks when we forward the email to outside titan. 2) email editor is too laggy while typing.]
A5: Very clear | B5: 26022 | C5: 45381 | D5: 5 | E5: Pro | F5: Hostinger | G5: NPS | H5: They get smaller and smaller until it is just one character PER LINE, this makes them unreadable | I5: the way the emails appear in threads is extremely annoying. They get smaller and smaller until it is just one character PER LINE, this makes them unreadable. When searching the inbox, emails come up that do not contain the search term at all. In certain threads TITAN decides it thinks an email thread is spam and blocks my email. [Improvement: Fix all the issues I just mentioned]
A6: Very clear | B6: 1193270 | C6: 44733 | D6: 7 | E6: Pro | F6: WordPress.com | G6: NPS | H6: The message block becomes thinner and thinner, until each word in the email becomes a new line | I6: Most features are good. However, the tiered layout of email threads makes older messages more and more difficult to read. The message block becomes thinner and thinner, until each word in the email becomes a new line.
A7: Moderate | B7: 8910983 | C7: 46251 | D7: 2 | E7: Pro | F7: Crazy Domains | G7: NPS | H7: when i go email to follow previous thread it formats copy so i cant read it | I7: when i go email to follow previous thread it formats copy so i cant read it and also jpegs dont show up [Improvement: see earlier comments]
A8: Moderate | B8: 6459991 | C8: 46211 | D8: 7 | E8: Pro | F8: WordPress.com | G8: NPS | H8: Formatting in emails can be funky when forwarding | I8: Formatting in emails can be funky when forwarding and navigating email chains can be frustrating.
A9: Moderate | B9: 2985139 | C9: 46055 | D9: 4 | E9: Pro | F9: Zyro | G9: NPS | H9: You cannot make any sense of the email history when there are several replies, replies on replies | I9: You cannot make any sense of the email history when there are several replies, replies on replies. If you want more information it will be consulting and chargeable, like any intellectual consulting work :)
A10: Moderate | B10: 648473 | C10: 45373 | D10: 6 | E10: Pro | F10: WordPress.com | G10: NPS | H10: navigating through email threads/viewing quoted emails | I10: The search function, navigating through email threads/viewing quoted emails, text formatting (especially on the app). Not all emojis are available, but I can live with that. [Improvement: Fix these things (at least the search function!)]

Sheet Attachment Discovery
A1: Classification Clarity | B1: Account ID | C1: Feedback Date | D1: NPS Score | E1: Plan | F1: Partner | G1: Source | H1: Highlighted Relevant Comment | I1: Full Feedback
A2: Very clear | B2: 7245148 | C2: 46148 | D2: 3 | E2: Pro | F2: WordPress.com | G2: NPS | H2: struggling to find a file attached to an email in the thread | I2: Email threads are a pain to view and manage - I often end up replying to the wrong email in the thread or struggling to find a file attached to an email in the thread [Improvement: fix the thread problem]
A3: Very clear | B3: 8039009 | C3: 46147 | D3: 3 | E3: Premium | F3: HostGator US | G3: NPS | H3: Attachments hard to find in long email string | I3: worse than Gmail. Spam keeps returning. Attachments hard to find in long email string. [Improvement: what I wrote above]
A4: Very clear | B4: 8023722 | C4: 46115 | D4: 3 | E4: Pro | F4: WordPress.com | G4: NPS | H4: you have to scroll to the bottom of the entire thread in order to see the attachments for a recent response | I4: The email threads are difficult to follow on mobile, often you have to scroll to the bottom of the entire thread in order to see the attachments for a recent response to the email.
A5: Very clear | B5: 7436174 | C5: 45954 | D5: 2 | E5: Pro | F5: Vodien | G5: NPS | H5: THE ATTACHMENTS FROM OTJHER EMAILS ARE IMPOSSIBLE TO FIND | I5: THE ATTACHMENTS FROM OTJHER EMAILS ARE IMPOSSIBLE TO FIND - PUT THEM ON THE BOTTOM OF THE PETR6TITENT EMAIL MNPOT AT THE TOP OR THE BOTTOM OF OVER 40 EMAILS IN THE THREAD- UNBELIEVABLE WASTE OF TIME [Improvement: SEE WHAT I SAID PREVIOUSLY]
A6: Very clear | B6: 3098843 | C6: 45928 | D6: 7 | E6: Premium | F6: name.com | G6: NPS | H6: i HAVE TO KEEP GOING BACK TO FIND ATTACHMENTS | I6: THE EMAIL CHAINS ARE VER CONFUSING. i HAVE TO KEEP GOING BACK TO FIND ATTACHMENTS. [Improvement: SIMPLIFY THE EMAIL STRUCTURES]
A7: Very clear | B7: 3486382 | C7: 45863 | D7: 6 | E7: Pro | F7: WordPress.com | G7: NPS | H7: if any attachment was linked to any message in the thread, I'd like an easier way to get to it rather than having the find the specific message | I7: I find it confusing how email threads are grouped together and would like an easier way to find attachments. The version on my laptop is a bit better than on my phone. [Improvement: In email threads, I'd like the most recent to show at the top, and older messages below, with the ability to collapse some or all if necessary. I'm not sure why some messages display above but when I scroll down they seem to be there too? It just seems confusing. And if any attachment was linked to any message in the thread, I'd like an easier way to get to it rather than having the find the specific message (on my phone specifically).]
A8: Very clear | B8: 3305096 | C8: 45792 | D8: 10 | E8: Pro | F8: WordPress.com | G8: NPS | H8: It is confusing to navigate through the whole email thread and see them at the end of the email history | I8: It is functional, intuitive, easy to use. [Improvement: The attachments for each email should be visible at the start of the message. It is confusing to navigate through the whole email thread and see them at the end of the email history; it would be simpler to see them in the header after the subject. It is a suggestion - or have the option to see the thread/email history or only the last email that arrived.]
A9: Very clear | B9: 4892608 | C9: 45612 | D9: 10 | E9: Free | F9: Hostinger | G9: NPS | H9: make attachments show up below the subject line instead of on the bottom of a 20 email thread | I9: Great software, great services. I just wish you would make attachments show up below the subject line instead of on the bottom of a 20 email thread.. [Improvement: Please show attachments at the top of the email rather than the bottom of email threads where there could be 20-30 emails and you would have to scroll down all 30 to reach the attachment]
A10: Very clear | B10: 4080419 | C10: 45357 | D10: 1 | E10: Free | F10: Hostinger | G10: NPS | H10: Attachments are hard to find in a long email thread | I10: The search bar does not search all through the emails like gmail. Downloads don't always work properly. Attachments are hard to find in a long email thread.
A11: Very clear | B11: 2842975 | C11: 45320 | D11: 4 | E11: Free | F11: Hostinger | G11: NPS | H11: I really have a hard time finding attachments in the email.... especially if its a continuous trail | I11: I really have a hard time finding attachments in the email.... especially if its a continuous trail [Improvement: improve how attachment appear in long email trails .. show attachment with its email body]
A12: Very clear | B12: 446034 | C12: 44837 | D12: 1 | E12: Pro | F12: WordPress.com | G12: NPS | H12: attachments are very difficult to find in a long email thread | I12: don't like the format at all, attachments are very difficult to find in a long email thread [Improvement: make attachment easy to find in email thread]
A13: Very clear | B13: 537081 | C13: 44697 | D13: 10 | E13: Pro | F13: WordPress.com | G13: NPS | H13: sometimes it is difficult to find related attachments in long chain of emails | I13: Very good UX, but sometimes it is difficult to find related attachments in long chain of emails. [Improvement: Change the way chain of emails work. Inserted attachments have to be shown not at the bottom of related chain, but in particular email it was inserted in.]
... A30: Moderate | B30: 511896 | C30: 44769 | D30: 8 | E30: Pro | F30: Hostinger | G30: NPS | H30: the search for attachments/ attachment content could be improved | I30: It's good but not outstanding [Improvement: Long conversation threads can be tedious and the search for attachments/ attachment content could be improved]

Sheet Attachment Carry-over
A1: Classification Clarity | B1: Account ID | C1: Feedback Date | D1: NPS Score | E1: Plan | F1: Partner | G1: Source | H1: Highlighted Relevant Comment | I1: Full Feedback
A2: Clear | B2: 6276279 | C2: 45663 | D2: 1 | E2: Premium | F2: HostGator | G2: NPS | H2: attached files do not come through in the email when they are replied to | I2: The email system is very bad, because attached files do not come through in the email when they are replied to. Another point is that email histories end up out of order. [Improvement: By fixing the system inputs so that emails work better.]

Sheet Message Rendering
A1: Classification Clarity | B1: Account ID | C1: Feedback Date | D1: NPS Score | E1: Plan | F1: Partner | G1: Source | H1: Highlighted Relevant Comment | I1: Full Feedback
A2: Very clear | B2: 3104383 | C2: 46158 | D2: 5 | E2: Premium | F2: name.com | G2: NPS | H2: Sometimes the text of email threads vanish under ... ellipses | I2: A lot of third party AI tools interact with gmail but not Titan. Links to my other emails seem to automatically disappear after a while. Contact management is not intuitive or easy. Sometimes the text of email threads vanish under ... ellipses. [Improvement: Transparent integration with third party AI and spam filter tools like gmail.]
A3: Very clear | B3: 3305982 | C3: 46146 | D3: 0 | E3: Free | F3: Hostinger | G3: NPS | H3: the newest email in a thread does not load and i cant see it until i press the reply button | I3: Cant block email addresses so constantly getting spammed by the same people sending follow up emails. Extremely often the newest email in a thread does not load and i cant see it until i press the reply button. Sometimes when i press tbe reply button it wont show me the top of the email where im typing my reply so i cant see what im typing. And even this little feedback box doesnt have autocorrect so im wasting time erasing and retyping to do this free labour of telling you to fix the most basic of issues which shouldnt even be issues.
A4: Very clear | B4: 7578799 | C4: 46128 | D4: 5 | E4: Pro | F4: WordPress.com | G4: NPS | H4: The root email is repeated in the chain over and over again | I4: The conversation view is awful. The root email is repeated in the chain over and over again. Plus if I am drating a reply in a chain and I click away it gets lost. Way too much scrolling involved. [Improvement: sort out conversation view.]
A5: Very clear | B5: 2975066 | C5: 46028 | D5: 3 | E5: Free | F5: Hostinger | G5: NPS | H5: Difficult to view trailing email showing multiple same email in trailing email | I5: Face lot of difficulty making email. Not a user friendly environment. Difficult to view trailing email showing multiple same email in trailing email. Many other functionality which are in outlook are not meeting the criteria [Improvement: Make user friendly environment]
A6: Very clear | B6: 4460025 | C6: 45680 | D6: 1 | E6: Pro | F6: WordPress.com | G6: NPS | H6: some emails are just repeatedly shown in a thread | I6: It frequently doesn't update the inbox with new emails when running in Chrome. Mine is currently 8 days behind. And the way it displays email chains is so confusing, I frequently can't find previous emails or figure out which came first - not to mention that some emails are just repeatedly shown in a thread. [Improvement: make it work in Chrome]
A7: Very clear | B7: 3136654 | C7: 45419 | D7: 1 | E7: Pro | F7: Hostinger | G7: NPS | H7: WITH OUT REPEATING THE FIRST MESSAGE OVER AND OER AGAIN | I7: ABSOULUTELY HATE THE WAY CONVERSATIONS ARE GROUPED. THEY NEED TO BE IN ORDER WITH OUT REPEATING THE FIRST MESSAGE OVER AND OER AGAIN, FOLLOW GMAIL!!!!! [Improvement: FOLLOW GMAIL.]
A8: Very clear | B8: 251318 | C8: 45379 | D8: 6 | E8: Pro | F8: Hostinger | G8: NPS | H8: Stacked emails are messy and full of duplicate messages | I8: Stacked emails are messy and full of duplicate messages. Reply and forward functions are awkward.
A9: Very clear | B9: 95826 | C9: 45312 | D9: 1 | E9: Premium | F9: Web.com - UK | G9: NPS | H9: sometimes same email two/three times | I9: very confusing layout, email trails not in date order, sometimes same email two/three times etc [Improvement: read previous comment]
A10: Very clear | B10: 3096850 | C10: 45258 | D10: 1 | E10: Pro | F10: name.com | G10: NPS | H10: messages are often repeated | I10: I absolutely detest the formatting of Titan. I have to scroll to the bottom of a long conversation to reply and messages are often repeated. [Improvement: Be a normal server and have the newest messages at the top of a conversation.]
A11: Very clear | B11: 1534777 | C11: 44979 | D11: 2 | E11: Pro | F11: Hostinger | G11: NPS | H11: Eliminate the repetitive messages in the inbox threads | I11: Unable to search fields in contacts. Inbox threads are very hard to follow. [Improvement: Give me searchable fields in contacts. Eliminate the repetitive messages in the inbox threads allowing new messages easier to find and read.]
A12: Very clear | B12: 926135 | C12: 44802 | D12: 6 | E12: Pro | F12: Hostinger | G12: NPS | H12: It is confusing how it shows several repetitions of the same email within one mail | I12: It is confusing how it shows several repetitions of the same email within one mail. It should only show, in chronological order, the start and end of each email thread. [Improvement: Absolutely!!]
A13: Clear | B13: 8910983 | C13: 46251 | D13: 2 | E13: Pro | F13: Crazy Domains | G13: NPS | H13: jpegs dont show up | I13: when i go email to follow previous thread it formats copy so i cant read it and also jpegs dont show up [Improvement: see earlier comments]
... A30: Moderate | B30: 1504384 | C30: 44978 | D30: 5 | E30: Pro | F30: WordPress.com | G30: NPS | H30: the filing of email chains is really confusing and repetitive | I30: the filing of email chains is really confusing and repetitive.

Sheet Attach Conversation
A1: Classification Clarity | B1: Account ID | C1: Feedback Date | D1: NPS Score | E1: Plan | F1: Partner | G1: Source | H1: Highlighted Relevant Comment | I1: Full Feedback
A2: Very clear | B2: 9494030 | C2: 46252 | D2: 3 | E2: Free | F2: Hostinger | G2: NPS | H2: Give an option to forward email threads as an attachment | I2: The options and tools available with the free trial are very limited. [Improvement: 1. Give an option to recover emails 2. Give an option to forward email threads as an attachment 3. Make it easier to find emails so they do not become a mess 4. Give more storage 5. Stop trying to charge for everything]
A3: Very clear | B3: 8525088 | C3: 46185 | D3: 1 | E3: Premium | F3: Hostgator Mexico | G3: NPS | H3: It is not possible to attach email threads to new emails | I3: It is not possible to attach email threads to new emails; email threads are confusing when forwarding.

Sheet Print Conversation
A1: Classification Clarity | B1: Account ID | C1: Feedback Date | D1: NPS Score | E1: Plan | F1: Partner | G1: Source | H1: Highlighted Relevant Comment | I1: Full Feedback
A2: Very clear | B2: 6178215 | C2: 45985 | D2: 8 | E2: Free | F2: Hostinger | G2: NPS | H2: In single message print .... it should print whole thread. In general print email ... it should avoid duplication print of same message | I2: email printing is not appropriate [Improvement: In single message print .... it should print whole thread. In general print email ... it should avoid duplication print of same message]
A3: Very clear | B3: 5465424 | C3: 45630 | D3: 7 | E3: Pro | F3: HostGator | G3: NPS | H3: when we need to print a chain of emails there are problems or difficulties | I3: The system is good, but when we need to print a chain of emails there are problems or difficulties. [Improvement: By organising the messages in a date sequence without repeating email chains or loose messages.]
A4: Very clear | B4: 1529723 | C4: 45369 | D4: 7 | E4: Pro | F4: Hostinger | G4: NPS | H4: often printing a message thread doesn't work | I4: I find it difficult to find messages and often printing a message thread doesn't work. [Improvement: see why I gave the score]
A5: Very clear | B5: 1726826 | C5: 44921 | D5: 5 | E5: Pro | F5: WordPress.com | G5: NPS | H5: I cannot print an email thread | I5: I cannot print an email thread, which has made working very hard these last few months [Improvement: by adding features like printing an email thread]
A6: Very clear | B6: 917360 | C6: 44692 | D6: 2 | E6: Pro | F6: WordPress.com | G6: NPS | H6: Most email threads can't be printed--it's a blank screen when I choose "print conversation." | I6: Can't work with individual emails, they are all in nightmarish THREADS. Can't file sent emails. If I delete one email in a THREAD, they all get deleted! Most email threads can't be printed--it's a blank screen when I choose "print conversation." SO MANY BUGS. ESPECIALLY the thread views. They are so freakishly complicated and difficult. I sent out an invitation to sixty people who all individually replied. Just imagine how easy it was to miss replies. [Improvement: Fix all the stuff I just listed!]
A7: Very clear | B7: 167088 | C7: 44290 | D7: 1 | E7: Free | F7: TSO Host | G7: NPS | H7: it prints the whole string, repeating some messages multiple times | I7: Difficult to use, If I want to print out 1 email from a chain of emails, it prints the whole string, repeating some messages multiple times. It I receive on "out of hours" message from 1 recipient from a message sent to multiple recipients, I cannot delete that one message from the string, as it deletes the whole chain.
A8: Moderate | B8: 181722 | C8: 44442 | D8: 6 | E8: Free | F8: TSO Host | G8: NPS | H8: Difficult to print individual emails in a conversation | I8: Difficult to print individual emails in a conversation. Printing emails doesn't show date and time. [Improvement: Enable individual emails in a conversation to be printed separately. When printing emails, show date and time of each.]
A9: Moderate | B9: 230774 | C9: 44441 | D9: 2 | E9: Pro | F9: WordPress.com | G9: NPS | H9: It makes printing individual e-mails tough | I9: I do not like the e-mail grouping. It makes printing individual e-mails tough. Somehow I got flagged as spam and my clients do not get my e-mails. I plan to switch soon.
A10: Moderate | B10: 140337 | C10: 44257 | D10: 1 | E10: Free | F10: TSO Host | G10: NPS | H10: you cannot print emails properly | I10: It's slow and sluggish. It isn't as advanced as, say, as hotmail. [Improvement: Get rid of the annoying email thread - and allow each email to be read individually. Instead you cannot print emails properly and trying to compose a message and then try and find it again is exhausting]
